{
"meta":{"test_sets":[],"test_metrics":[],"learn_metrics":[{"best_value":"Min","name":"Logloss"}],"launch_mode":"Train","parameters":"","iteration_count":1000,"learn_sets":["learn"],"name":"experiment"},
"iterations":[
{"learn":[0.6539145802],"iteration":0,"passed_time":0.004670220986,"remaining_time":4.665550765},
{"learn":[0.616783543],"iteration":1,"passed_time":0.009809111032,"remaining_time":4.894746405},
{"learn":[0.5839765655],"iteration":2,"passed_time":0.01502346965,"remaining_time":4.992799746},
{"learn":[0.5515044678],"iteration":3,"passed_time":0.02054734042,"remaining_time":5.116287764},
{"learn":[0.5227808026],"iteration":4,"passed_time":0.02616666609,"remaining_time":5.207166551},
{"learn":[0.4922115794],"iteration":5,"passed_time":0.03195552264,"remaining_time":5.293964917},
{"learn":[0.4662688024],"iteration":6,"passed_time":0.03802455873,"remaining_time":5.39405526},
{"learn":[0.4441583638],"iteration":7,"passed_time":0.04343846872,"remaining_time":5.386370122},
{"learn":[0.4225451316],"iteration":8,"passed_time":0.04820068876,"remaining_time":5.307431395},
{"learn":[0.4005461182],"iteration":9,"passed_time":0.05314864645,"remaining_time":5.261715999},
{"learn":[0.3804873534],"iteration":10,"passed_time":0.05850062157,"remaining_time":5.259737703},
{"learn":[0.3621976087],"iteration":11,"passed_time":0.06351663912,"remaining_time":5.229536621},
{"learn":[0.3461175644],"iteration":12,"passed_time":0.06862790067,"remaining_time":5.210441381},
{"learn":[0.3297468245],"iteration":13,"passed_time":0.07506952321,"remaining_time":5.287039277},
{"learn":[0.3151193054],"iteration":14,"passed_time":0.08157620596,"remaining_time":5.356837525},
{"learn":[0.301279665],"iteration":15,"passed_time":0.08677798158,"remaining_time":5.336845867},
{"learn":[0.2890602687],"iteration":16,"passed_time":0.09194452699,"remaining_time":5.316557061},
{"learn":[0.2774879008],"iteration":17,"passed_time":0.09745488698,"remaining_time":5.316705501},
{"learn":[0.2665686509],"iteration":18,"passed_time":0.1030147331,"remaining_time":5.318813327},
{"learn":[0.2571283066],"iteration":19,"passed_time":0.1081193802,"remaining_time":5.29784963},
{"learn":[0.2478840371],"iteration":20,"passed_time":0.1137306369,"remaining_time":5.302013975},
{"learn":[0.2385884711],"iteration":21,"passed_time":0.1189203147,"remaining_time":5.286548535},
{"learn":[0.2306460448],"iteration":22,"passed_time":0.1240474729,"remaining_time":5.269320915},
{"learn":[0.2228722903],"iteration":23,"passed_time":0.128801041,"remaining_time":5.237909},
{"learn":[0.2155127892],"iteration":24,"passed_time":0.1347463735,"remaining_time":5.255108566},
{"learn":[0.2088493353],"iteration":25,"passed_time":0.1401062984,"remaining_time":5.248597485},
{"learn":[0.203013691],"iteration":26,"passed_time":0.1449935247,"remaining_time":5.22513702},
{"learn":[0.1972519118],"iteration":27,"passed_time":0.1500664185,"remaining_time":5.209448528},
{"learn":[0.1908022553],"iteration":28,"passed_time":0.1550658383,"remaining_time":5.192032033},
{"learn":[0.1851311573],"iteration":29,"passed_time":0.1602672748,"remaining_time":5.181975218},
{"learn":[0.1803043827],"iteration":30,"passed_time":0.1651665359,"remaining_time":5.162786235},
{"learn":[0.1759786264],"iteration":31,"passed_time":0.1704481186,"remaining_time":5.156055588},
{"learn":[0.1714938905],"iteration":32,"passed_time":0.175528197,"remaining_time":5.143508074},
{"learn":[0.1671725736],"iteration":33,"passed_time":0.1807226262,"remaining_time":5.134648732},
{"learn":[0.1632978638],"iteration":34,"passed_time":0.1855642283,"remaining_time":5.116270865},
{"learn":[0.1596474223],"iteration":35,"passed_time":0.1911181002,"remaining_time":5.117718016},
{"learn":[0.156439718],"iteration":36,"passed_time":0.1980611534,"remaining_time":5.154942992},
{"learn":[0.1530219701],"iteration":37,"passed_time":0.2056253529,"remaining_time":5.205568144},
{"learn":[0.1496121478],"iteration":38,"passed_time":0.2114159684,"remaining_time":5.209506297},
{"learn":[0.1469504595],"iteration":39,"passed_time":0.2170159626,"remaining_time":5.208383103},
{"learn":[0.1442979869],"iteration":40,"passed_time":0.2223615922,"remaining_time":5.201091875},
{"learn":[0.1416966249],"iteration":41,"passed_time":0.2277597358,"remaining_time":5.195091117},
{"learn":[0.1394064352],"iteration":42,"passed_time":0.2330562258,"remaining_time":5.186856003},
{"learn":[0.1374607478],"iteration":43,"passed_time":0.2387898497,"remaining_time":5.18825219},
{"learn":[0.1355157345],"iteration":44,"passed_time":0.2437840615,"remaining_time":5.173639528},
{"learn":[0.1335064902],"iteration":45,"passed_time":0.2495356619,"remaining_time":5.175152639},
{"learn":[0.1313867504],"iteration":46,"passed_time":0.2551683851,"remaining_time":5.173946192},
{"learn":[0.1297291671],"iteration":47,"passed_time":0.2597966834,"remaining_time":5.15263422},
{"learn":[0.1276393289],"iteration":48,"passed_time":0.2646110533,"remaining_time":5.135614525},
{"learn":[0.1261844679],"iteration":49,"passed_time":0.2698851572,"remaining_time":5.127817986},
{"learn":[0.1248789291],"iteration":50,"passed_time":0.2744695556,"remaining_time":5.107286437},
{"learn":[0.1235396653],"iteration":51,"passed_time":0.2790368095,"remaining_time":5.087055682},
{"learn":[0.1221337881],"iteration":52,"passed_time":0.2839053712,"remaining_time":5.072799746},
{"learn":[0.1207886439],"iteration":53,"passed_time":0.2891028767,"remaining_time":5.0646541},
{"learn":[0.1196474306],"iteration":54,"passed_time":0.2940751861,"remaining_time":5.05274638},
{"learn":[0.1183643908],"iteration":55,"passed_time":0.299119693,"remaining_time":5.042303396},
{"learn":[0.1173255845],"iteration":56,"passed_time":0.3043780531,"remaining_time":5.03558779},
{"learn":[0.1162310656],"iteration":57,"passed_time":0.3100961151,"remaining_time":5.036388628},
{"learn":[0.1150988472],"iteration":58,"passed_time":0.3154388481,"remaining_time":5.030982306},
{"learn":[0.1141382756],"iteration":59,"passed_time":0.3201432756,"remaining_time":5.015577984},
{"learn":[0.113230523],"iteration":60,"passed_time":0.3253586046,"remaining_time":5.008389011},
{"learn":[0.1120002787],"iteration":61,"passed_time":0.3309209949,"remaining_time":5.006514407},
{"learn":[0.1111743634],"iteration":62,"passed_time":0.3359786989,"remaining_time":4.997016522},
{"learn":[0.1101754995],"iteration":63,"passed_time":0.3410309482,"remaining_time":4.987577618},
{"learn":[0.1093875045],"iteration":64,"passed_time":0.345845228,"remaining_time":4.974850587},
{"learn":[0.1087445319],"iteration":65,"passed_time":0.350584366,"remaining_time":4.961299968},
{"learn":[0.1079053683],"iteration":66,"passed_time":0.3554502396,"remaining_time":4.949777217},
{"learn":[0.1071380824],"iteration":67,"passed_time":0.3601806223,"remaining_time":4.936593234},
{"learn":[0.1063926214],"iteration":68,"passed_time":0.3648491395,"remaining_time":4.922819549},
{"learn":[0.105883968],"iteration":69,"passed_time":0.3697083578,"remaining_time":4.91183961},
{"learn":[0.1053583707],"iteration":70,"passed_time":0.3746867323,"remaining_time":4.902591188},
{"learn":[0.1046600923],"iteration":71,"passed_time":0.380477168,"remaining_time":4.903927943},
{"learn":[0.1041786792],"iteration":72,"passed_time":0.3859321349,"remaining_time":4.90080944},
{"learn":[0.1036733728],"iteration":73,"passed_time":0.3912045382,"remaining_time":4.895343276},
{"learn":[0.1030797559],"iteration":74,"passed_time":0.3966641369,"remaining_time":4.892191022},
{"learn":[0.1024653834],"iteration":75,"passed_time":0.4022471037,"remaining_time":4.890477945},
{"learn":[0.1019292107],"iteration":76,"passed_time":0.4075825992,"remaining_time":4.88569791},
{"learn":[0.1015817449],"iteration":77,"passed_time":0.4132612421,"remaining_time":4.884959811},
{"learn":[0.1012732106],"iteration":78,"passed_time":0.4183228202,"remaining_time":4.876902752},
{"learn":[0.1006373618],"iteration":79,"passed_time":0.4233394043,"remaining_time":4.868403149},
{"learn":[0.100190987],"iteration":80,"passed_time":0.4281550207,"remaining_time":4.857709433},
{"learn":[0.0998760726],"iteration":81,"passed_time":0.4330928146,"remaining_time":4.848526876},
{"learn":[0.09957789285],"iteration":82,"passed_time":0.4382023481,"remaining_time":4.841344014},
{"learn":[0.09911869976],"iteration":83,"passed_time":0.4438933473,"remaining_time":4.840551264},
{"learn":[0.0987738488],"iteration":84,"passed_time":0.4490947377,"remaining_time":4.834372764},
{"learn":[0.09835523735],"iteration":85,"passed_time":0.4544864806,"remaining_time":4.830240038},
{"learn":[0.09801013072],"iteration":86,"passed_time":0.4608667899,"remaining_time":4.836452634},
{"learn":[0.09767724972],"iteration":87,"passed_time":0.4676362065,"remaining_time":4.846411594},
{"learn":[0.09741942499],"iteration":88,"passed_time":0.4749439705,"remaining_time":4.861505136},
{"learn":[0.09717212918],"iteration":89,"passed_time":0.4802143699,"remaining_time":4.855500852},
{"learn":[0.0967848488],"iteration":90,"passed_time":0.4856124871,"remaining_time":4.85078847},
{"learn":[0.096568855],"iteration":91,"passed_time":0.4908297637,"remaining_time":4.844276364},
{"learn":[0.09620487536],"iteration":92,"passed_time":0.4962288105,"remaining_time":4.83956485},
{"learn":[0.09603375147],"iteration":93,"passed_time":0.5015288448,"remaining_time":4.833884397},
{"learn":[0.09584082598],"iteration":94,"passed_time":0.5065447907,"remaining_time":4.825505638},
{"learn":[0.09547828738],"iteration":95,"passed_time":0.5114883662,"remaining_time":4.816515448},
{"learn":[0.09509879328],"iteration":96,"passed_time":0.5166972895,"remaining_time":4.810078891},
{"learn":[0.09493728022],"iteration":97,"passed_time":0.5216240781,"remaining_time":4.801070597},
{"learn":[0.0947791722],"iteration":98,"passed_time":0.5266477959,"remaining_time":4.79302691},
{"learn":[0.0945468737],"iteration":99,"passed_time":0.5321606832,"remaining_time":4.789446149},
{"learn":[0.09431718418],"iteration":100,"passed_time":0.5373072229,"remaining_time":4.782566271},
{"learn":[0.09415671123],"iteration":101,"passed_time":0.5424009456,"remaining_time":4.775255384},
{"learn":[0.09394126363],"iteration":102,"passed_time":0.5475227047,"remaining_time":4.76823171},
{"learn":[0.09378867574],"iteration":103,"passed_time":0.5527751156,"remaining_time":4.762370226},
{"learn":[0.09362951019],"iteration":104,"passed_time":0.5578040169,"remaining_time":4.754615192},
{"learn":[0.09343245333],"iteration":105,"passed_time":0.5632179434,"remaining_time":4.750158881},
{"learn":[0.09318408835],"iteration":106,"passed_time":0.568328493,"remaining_time":4.74315275},
{"learn":[0.09295528787],"iteration":107,"passed_time":0.5736573601,"remaining_time":4.737984863},
{"learn":[0.09283041682],"iteration":108,"passed_time":0.5789835673,"remaining_time":4.732792279},
{"learn":[0.09245421155],"iteration":109,"passed_time":0.58406885,"remaining_time":4.725647968},
{"learn":[0.09224384247],"iteration":110,"passed_time":0.5890275036,"remaining_time":4.717526583},
{"learn":[0.09203437985],"iteration":111,"passed_time":0.5938655288,"remaining_time":4.708505264},
{"learn":[0.09163005681],"iteration":112,"passed_time":0.5986770853,"remaining_time":4.699350218},
{"learn":[0.09131259148],"iteration":113,"passed_time":0.6035665518,"remaining_time":4.690876885},
{"learn":[0.09124433949],"iteration":114,"passed_time":0.6086282233,"remaining_time":4.68379111},
{"learn":[0.09107894491],"iteration":115,"passed_time":0.6134701831,"remaining_time":4.675065878},
{"learn":[0.09088699562],"iteration":116,"passed_time":0.6189129982,"remaining_time":4.670941687},
{"learn":[0.09069391906],"iteration":117,"passed_time":0.6254778313,"remaining_time":4.675181756},
{"learn":[0.0905567759],"iteration":118,"passed_time":0.6314257176,"remaining_time":4.67467275},
{"learn":[0.09044083583],"iteration":119,"passed_time":0.6375453628,"remaining_time":4.675332661},
{"learn":[0.09029295457],"iteration":120,"passed_time":0.6427388098,"remaining_time":4.66915218},
{"learn":[0.09010895426],"iteration":121,"passed_time":0.6480353414,"remaining_time":4.663729752},
{"learn":[0.089918876],"iteration":122,"passed_time":0.6533822922,"remaining_time":4.658668864},
{"learn":[0.08986907285],"iteration":123,"passed_time":0.658382098,"remaining_time":4.65115095},
{"learn":[0.08978513208],"iteration":124,"passed_time":0.6636745302,"remaining_time":4.645721712},
{"learn":[0.08961089367],"iteration":125,"passed_time":0.6692230467,"remaining_time":4.642070975},
{"learn":[0.08950560454],"iteration":126,"passed_time":0.6748117893,"remaining_time":4.638666867},
{"learn":[0.08936516674],"iteration":127,"passed_time":0.6801816803,"remaining_time":4.633737697},
{"learn":[0.08932341135],"iteration":128,"passed_time":0.6847423004,"remaining_time":4.623337548},
{"learn":[0.08922468245],"iteration":129,"passed_time":0.6904010294,"remaining_time":4.62037612},
{"learn":[0.08910665054],"iteration":130,"passed_time":0.6958581462,"remaining_time":4.6160361},
{"learn":[0.0889893624],"iteration":131,"passed_time":0.7009225048,"remaining_time":4.609096471},
{"learn":[0.08887466001],"iteration":132,"passed_time":0.7061357451,"remaining_time":4.603155571},
{"learn":[0.08881462428],"iteration":133,"passed_time":0.7111240335,"remaining_time":4.595771739},
{"learn":[0.08869092699],"iteration":134,"passed_time":0.7164318926,"remaining_time":4.590471016},
{"learn":[0.08856670673],"iteration":135,"passed_time":0.7214476395,"remaining_time":4.583314416},
{"learn":[0.08848826284],"iteration":136,"passed_time":0.7262941555,"remaining_time":4.575123038},
{"learn":[0.08837911543],"iteration":137,"passed_time":0.7317716945,"remaining_time":4.570921744},
{"learn":[0.08820120469],"iteration":138,"passed_time":0.7372286895,"remaining_time":4.566574832},
{"learn":[0.08804348018],"iteration":139,"passed_time":0.7430136785,"remaining_time":4.564226882},
{"learn":[0.08798310744],"iteration":140,"passed_time":0.7474275456,"remaining_time":4.553477033},
{"learn":[0.08778066991],"iteration":141,"passed_time":0.7529157826,"remaining_time":4.549308038},
{"learn":[0.08759603624],"iteration":142,"passed_time":0.7578646319,"remaining_time":4.541888039},
{"learn":[0.08741127473],"iteration":143,"passed_time":0.7628257036,"remaining_time":4.534575016},
{"learn":[0.08730636329],"iteration":144,"passed_time":0.7683186863,"remaining_time":4.530430874},
{"learn":[0.0872072567],"iteration":145,"passed_time":0.7729402683,"remaining_time":4.521171158},
{"learn":[0.08714541968],"iteration":146,"passed_time":0.7776439545,"remaining_time":4.512450974},
{"learn":[0.08704595864],"iteration":147,"passed_time":0.7835221524,"remaining_time":4.510546445},
{"learn":[0.08690398682],"iteration":148,"passed_time":0.7899470279,"remaining_time":4.511710877},
{"learn":[0.08677392104],"iteration":149,"passed_time":0.795790764,"remaining_time":4.509480996},
{"learn":[0.08670501825],"iteration":150,"passed_time":0.8015091601,"remaining_time":4.506498523},
{"learn":[0.08659644029],"iteration":151,"passed_time":0.807820094,"remaining_time":4.506785787},
{"learn":[0.08641579854],"iteration":152,"passed_time":0.8140660575,"remaining_time":4.506627129},
{"learn":[0.08632463512],"iteration":153,"passed_time":0.8200817831,"remaining_time":4.505124601},
{"learn":[0.0862624204],"iteration":154,"passed_time":0.825709601,"remaining_time":4.501449115},
{"learn":[0.08616490012],"iteration":155,"passed_time":0.8313320091,"remaining_time":4.497719331},
{"learn":[0.08609986142],"iteration":156,"passed_time":0.8365078227,"remaining_time":4.491567481},
{"learn":[0.08599330556],"iteration":157,"passed_time":0.8416443906,"remaining_time":4.485218841},
{"learn":[0.08592472236],"iteration":158,"passed_time":0.8477738422,"remaining_time":4.484137115},
{"learn":[0.08579469726],"iteration":159,"passed_time":0.8530393621,"remaining_time":4.478456651},
{"learn":[0.08570110498],"iteration":160,"passed_time":0.8584721734,"remaining_time":4.473653127},
{"learn":[0.08551735453],"iteration":161,"passed_time":0.8644912801,"remaining_time":4.471874646},
{"learn":[0.08545445415],"iteration":162,"passed_time":0.8699508218,"remaining_time":4.467170784},
{"learn":[0.08538260536],"iteration":163,"passed_time":0.8749180712,"remaining_time":4.459948216},
{"learn":[0.08533630022],"iteration":164,"passed_time":0.8798709478,"remaining_time":4.452680251},
{"learn":[0.08524604908],"iteration":165,"passed_time":0.8845984647,"remaining_time":4.444307949},
{"learn":[0.08519213198],"iteration":166,"passed_time":0.8893751183,"remaining_time":4.436224393},
{"learn":[0.08510221204],"iteration":167,"passed_time":0.8943458332,"remaining_time":4.429141269},
{"learn":[0.08496793934],"iteration":168,"passed_time":0.8992140604,"remaining_time":4.421579197},
{"learn":[0.08492925198],"iteration":169,"passed_time":0.9041690394,"remaining_time":4.414472369},
{"learn":[0.08474767471],"iteration":170,"passed_time":0.9096050226,"remaining_time":4.409722595},
{"learn":[0.08469414693],"iteration":171,"passed_time":0.9150268548,"remaining_time":4.40489672},
{"learn":[0.08464083995],"iteration":172,"passed_time":0.9204029811,"remaining_time":4.399845464},
{"learn":[0.08456649838],"iteration":173,"passed_time":0.9258642456,"remaining_time":4.395194637},
{"learn":[0.08449295869],"iteration":174,"passed_time":0.9313060211,"remaining_time":4.390442671},
{"learn":[0.08441969791],"iteration":175,"passed_time":0.9369160793,"remaining_time":4.386470735},
{"learn":[0.08435958084],"iteration":176,"passed_time":0.9423790328,"remaining_time":4.381796294},
{"learn":[0.08427476266],"iteration":177,"passed_time":0.9479888414,"remaining_time":4.377791167},
{"learn":[0.08421333819],"iteration":178,"passed_time":0.9532227366,"remaining_time":4.372043948},
{"learn":[0.08408118638],"iteration":179,"passed_time":0.9587071443,"remaining_time":4.367443657},
{"learn":[0.08401216157],"iteration":180,"passed_time":0.9639168303,"remaining_time":4.361590519},
{"learn":[0.08394139356],"iteration":181,"passed_time":0.9686717025,"remaining_time":4.353700289},
{"learn":[0.08390263066],"iteration":182,"passed_time":0.9735798655,"remaining_time":4.346528689},
{"learn":[0.08385773751],"iteration":183,"passed_time":0.9787052311,"remaining_time":4.340344938},
{"learn":[0.0837685439],"iteration":184,"passed_time":0.9836244352,"remaining_time":4.333264404},
{"learn":[0.08369046027],"iteration":185,"passed_time":0.9881410116,"remaining_time":4.324445072},
{"learn":[0.08361568872],"iteration":186,"passed_time":0.9928798343,"remaining_time":4.316637996},
{"learn":[0.08347962634],"iteration":187,"passed_time":0.9980919627,"remaining_time":4.310907839},
{"learn":[0.08343673206],"iteration":188,"passed_time":1.003002201,"remaining_time":4.303887752},
{"learn":[0.08324922212],"iteration":189,"passed_time":1.008511725,"remaining_time":4.299444724},
{"learn":[0.08316551377],"iteration":190,"passed_time":1.013427028,"remaining_time":4.292473643},
{"learn":[0.08312552482],"iteration":191,"passed_time":1.01819158,"remaining_time":4.284889565},
{"learn":[0.08308042249],"iteration":192,"passed_time":1.022742323,"remaining_time":4.276440699},
{"learn":[0.08301083404],"iteration":193,"passed_time":1.027772012,"remaining_time":4.270021864},
{"learn":[0.08296954931],"iteration":194,"passed_time":1.032848282,"remaining_time":4.263809573},
{"learn":[0.08289512059],"iteration":195,"passed_time":1.038197165,"remaining_time":4.258727146},
{"learn":[0.08283392855],"iteration":196,"passed_time":1.04343216,"remaining_time":4.253177791},
{"learn":[0.08278012185],"iteration":197,"passed_time":1.048661773,"remaining_time":4.247609806},
{"learn":[0.08272038828],"iteration":198,"passed_time":1.054373457,"remaining_time":4.243985623},
{"learn":[0.08265030012],"iteration":199,"passed_time":1.059647775,"remaining_time":4.238591101},
{"learn":[0.08254258213],"iteration":200,"passed_time":1.064764878,"remaining_time":4.232572825},
{"learn":[0.08249101254],"iteration":201,"passed_time":1.069902945,"remaining_time":4.226646286},
{"learn":[0.08243999496],"iteration":202,"passed_time":1.074756856,"remaining_time":4.219611894},
{"learn":[0.082401203],"iteration":203,"passed_time":1.079649186,"remaining_time":4.212748785},
{"learn":[0.08238293429],"iteration":204,"passed_time":1.084430006,"remaining_time":4.205472463},
{"learn":[0.08233970299],"iteration":205,"passed_time":1.089189585,"remaining_time":4.198138497},
{"learn":[0.08225192719],"iteration":206,"passed_time":1.094084334,"remaining_time":4.191347233},
{"learn":[0.08220374521],"iteration":207,"passed_time":1.099013369,"remaining_time":4.18470475},
{"learn":[0.08216416881],"iteration":208,"passed_time":1.104174651,"remaining_time":4.178957649},
{"learn":[0.08208656747],"iteration":209,"passed_time":1.109271964,"remaining_time":4.172975484},
{"learn":[0.082021982],"iteration":210,"passed_time":1.115069995,"remaining_time":4.169621926},
{"learn":[0.08194836677],"iteration":211,"passed_time":1.120379804,"remaining_time":4.164430592},
{"learn":[0.08189370009],"iteration":212,"passed_time":1.125616641,"remaining_time":4.158968528},
{"learn":[0.08183614552],"iteration":213,"passed_time":1.131101845,"remaining_time":4.154420796},
{"learn":[0.08174505183],"iteration":214,"passed_time":1.136350619,"remaining_time":4.149001096},
{"learn":[0.08167986786],"iteration":215,"passed_time":1.142027212,"remaining_time":4.145135807},
{"learn":[0.08164070984],"iteration":216,"passed_time":1.148393871,"remaining_time":4.143743785},
{"learn":[0.08161592738],"iteration":217,"passed_time":1.154066215,"remaining_time":4.139815504},
{"learn":[0.08157759446],"iteration":218,"passed_time":1.159853568,"remaining_time":4.136281446},
{"learn":[0.08150906937],"iteration":219,"passed_time":1.165667524,"remaining_time":4.13282122},
{"learn":[0.08142964929],"iteration":220,"passed_time":1.172065574,"remaining_time":4.131398563},
{"learn":[0.08138903279],"iteration":221,"passed_time":1.177842505,"remaining_time":4.127754365},
{"learn":[0.0813768304],"iteration":222,"passed_time":1.183137153,"remaining_time":4.122410619},
{"learn":[0.08133154213],"iteration":223,"passed_time":1.18854742,"remaining_time":4.117467849},
{"learn":[0.08128853745],"iteration":224,"passed_time":1.194064416,"remaining_time":4.112888543},
{"learn":[0.08119994234],"iteration":225,"passed_time":1.199470987,"remaining_time":4.107922761},
{"learn":[0.08119109852],"iteration":226,"passed_time":1.204330597,"remaining_time":4.101090534},
{"learn":[0.08116173726],"iteration":227,"passed_time":1.211532595,"remaining_time":4.102206857},
{"learn":[0.08109686126],"iteration":228,"passed_time":1.216958173,"remaining_time":4.097269656},
{"learn":[0.08106261905],"iteration":229,"passed_time":1.222185951,"remaining_time":4.091666009},
{"learn":[0.08103596556],"iteration":230,"passed_time":1.227404784,"remaining_time":4.08603584},
{"learn":[0.08098411124],"iteration":231,"passed_time":1.232967522,"remaining_time":4.081547657},
{"learn":[0.08090717812],"iteration":232,"passed_time":1.238403459,"remaining_time":4.076632844},
{"learn":[0.08087233742],"iteration":233,"passed_time":1.243906667,"remaining_time":4.071933791},
{"learn":[0.08082110484],"iteration":234,"passed_time":1.250075651,"remaining_time":4.069395204},
{"learn":[0.08078420135],"iteration":235,"passed_time":1.255929447,"remaining_time":4.065805497},
{"learn":[0.08074392768],"iteration":236,"passed_time":1.261717568,"remaining_time":4.06198525},
{"learn":[0.08070818632],"iteration":237,"passed_time":1.268957528,"remaining_time":4.062796792},
{"learn":[0.08063976581],"iteration":238,"passed_time":1.276398804,"remaining_time":4.064181966},
{"learn":[0.08054078125],"iteration":239,"passed_time":1.28327721,"remaining_time":4.063711167},
{"learn":[0.08049773589],"iteration":240,"passed_time":1.289505623,"remaining_time":4.061140117},
{"learn":[0.08044389433],"iteration":241,"passed_time":1.294881948,"remaining_time":4.055869904},
{"learn":[0.08040618315],"iteration":242,"passed_time":1.300752819,"remaining_time":4.05213944},
{"learn":[0.08039356821],"iteration":243,"passed_time":1.306653414,"remaining_time":4.048483528},
{"learn":[0.08035431722],"iteration":244,"passed_time":1.311853724,"remaining_time":4.042651273},
{"learn":[0.08031112078],"iteration":245,"passed_time":1.317103564,"remaining_time":4.036975963},
{"learn":[0.08028048699],"iteration":246,"passed_time":1.322297881,"remaining_time":4.031134837},
{"learn":[0.0801747853],"iteration":247,"passed_time":1.328151386,"remaining_time":4.027297751},
{"learn":[0.08012155386],"iteration":248,"passed_time":1.333545717,"remaining_time":4.022059572},
{"learn":[0.08005660813],"iteration":249,"passed_time":1.338589886,"remaining_time":4.015769657},
{"learn":[0.08000517218],"iteration":250,"passed_time":1.344656314,"remaining_time":4.012540157},
{"learn":[0.07995850097],"iteration":251,"passed_time":1.349683346,"remaining_time":4.006202949},
{"learn":[0.07994310854],"iteration":252,"passed_time":1.354426156,"remaining_time":3.999036912},
{"learn":[0.07985297361],"iteration":253,"passed_time":1.3596749,"remaining_time":3.993375886},
{"learn":[0.07978174656],"iteration":254,"passed_time":1.365044483,"remaining_time":3.988071138},
{"learn":[0.07974660369],"iteration":255,"passed_time":1.369838524,"remaining_time":3.981093209},
{"learn":[0.07972784689],"iteration":256,"passed_time":1.3747234,"remaining_time":3.974394887},
{"learn":[0.07969906089],"iteration":257,"passed_time":1.379926017,"remaining_time":3.968624437},
{"learn":[0.07967647486],"iteration":258,"passed_time":1.385336183,"remaining_time":3.963452167},
{"learn":[0.07964305776],"iteration":259,"passed_time":1.390491156,"remaining_time":3.957551751},
{"learn":[0.07957674653],"iteration":260,"passed_time":1.395502212,"remaining_time":3.951249558},
{"learn":[0.07954479953],"iteration":261,"passed_time":1.400770545,"remaining_time":3.945681916},
{"learn":[0.07950157404],"iteration":262,"passed_time":1.406181113,"remaining_time":3.940515135},
{"learn":[0.07946891233],"iteration":263,"passed_time":1.411289736,"remaining_time":3.93450472},
{"learn":[0.07939017209],"iteration":264,"passed_time":1.416566052,"remaining_time":3.92896622},
{"learn":[0.0793607353],"iteration":265,"passed_time":1.422100169,"remaining_time":3.924141067},
{"learn":[0.07928619617],"iteration":266,"passed_time":1.427591671,"remaining_time":3.919193613},
{"learn":[0.07926175073],"iteration":267,"passed_time":1.433104037,"remaining_time":3.914299087},
{"learn":[0.07919742674],"iteration":268,"passed_time":1.439000363,"remaining_time":3.910443365},
{"learn":[0.07908870351],"iteration":269,"passed_time":1.444607234,"remaining_time":3.905789928},
{"learn":[0.07906122491],"iteration":270,"passed_time":1.450469624,"remaining_time":3.901816812},
{"learn":[0.07902494316],"iteration":271,"passed_time":1.456147438,"remaining_time":3.897335791},
{"learn":[0.07897010216],"iteration":272,"passed_time":1.462858541,"remaining_time":3.895597654},
{"learn":[0.07890787582],"iteration":273,"passed_time":1.468043017,"remaining_time":3.889778214},
{"learn":[0.07888284932],"iteration":274,"passed_time":1.473355131,"remaining_time":3.884299891},
{"learn":[0.07884394696],"iteration":275,"passed_time":1.478969132,"remaining_time":3.879614679},
{"learn":[0.07880472501],"iteration":276,"passed_time":1.48408529,"remaining_time":3.873623337},
{"learn":[0.07875177248],"iteration":277,"passed_time":1.489188951,"remaining_time":3.867605838},
{"learn":[0.07868006896],"iteration":278,"passed_time":1.494827592,"remaining_time":3.862977397},
{"learn":[0.07866150972],"iteration":279,"passed_time":1.500368396,"remaining_time":3.858090161},
{"learn":[0.07861396691],"iteration":280,"passed_time":1.505391718,"remaining_time":3.851874183},
{"learn":[0.07857453578],"iteration":281,"passed_time":1.510596292,"remaining_time":3.846128147},
{"learn":[0.07850249524],"iteration":282,"passed_time":1.515667705,"remaining_time":3.840048566},
{"learn":[0.07844112306],"iteration":283,"passed_time":1.520938126,"remaining_time":3.834477811},
{"learn":[0.07838213907],"iteration":284,"passed_time":1.526271801,"remaining_time":3.829067851},
{"learn":[0.07833491585],"iteration":285,"passed_time":1.53149509,"remaining_time":3.823382846},
{"learn":[0.07829420056],"iteration":286,"passed_time":1.538320139,"remaining_time":3.821680346},
{"learn":[0.07825298556],"iteration":287,"passed_time":1.544824734,"remaining_time":3.819150036},
{"learn":[0.07822750001],"iteration":288,"passed_time":1.551215845,"remaining_time":3.81631303},
{"learn":[0.07819776106],"iteration":289,"passed_time":1.556989378,"remaining_time":3.811939512},
{"learn":[0.0781884582],"iteration":290,"passed_time":1.562161088,"remaining_time":3.806090074},
{"learn":[0.0781702476],"iteration":291,"passed_time":1.567215281,"remaining_time":3.79996034},
{"learn":[0.07811250708],"iteration":292,"passed_time":1.573661987,"remaining_time":3.797198037},
{"learn":[0.07808089129],"iteration":293,"passed_time":1.57915235,"remaining_time":3.792114146},
{"learn":[0.07802138434],"iteration":294,"passed_time":1.585822937,"remaining_time":3.789848035},
{"learn":[0.07795829802],"iteration":295,"passed_time":1.591957121,"remaining_time":3.786276397},
{"learn":[0.07794060457],"iteration":296,"passed_time":1.597312443,"remaining_time":3.78084393},
{"learn":[0.07792941905],"iteration":297,"passed_time":1.602662318,"remaining_time":3.775399151},
{"learn":[0.07790553143],"iteration":298,"passed_time":1.607660642,"remaining_time":3.769130804},
{"learn":[0.07788044101],"iteration":299,"passed_time":1.612680681,"remaining_time":3.762921589},
{"learn":[0.07783696566],"iteration":300,"passed_time":1.617568707,"remaining_time":3.756413708},
{"learn":[0.07779447813],"iteration":301,"passed_time":1.622638515,"remaining_time":3.750336699},
{"learn":[0.07775533753],"iteration":302,"passed_time":1.627635688,"remaining_time":3.744099255},
{"learn":[0.07768357009],"iteration":303,"passed_time":1.6329511,"remaining_time":3.738598572},
{"learn":[0.07763385991],"iteration":304,"passed_time":1.637964108,"remaining_time":3.732410018},
{"learn":[0.07759796747],"iteration":305,"passed_time":1.642856522,"remaining_time":3.725955641},
{"learn":[0.07755599708],"iteration":306,"passed_time":1.647800314,"remaining_time":3.719627419},
{"learn":[0.0775139744],"iteration":307,"passed_time":1.652922165,"remaining_time":3.713708241},
{"learn":[0.0774186796],"iteration":308,"passed_time":1.657926209,"remaining_time":3.707530777},
{"learn":[0.07738324621],"iteration":309,"passed_time":1.662708253,"remaining_time":3.700866756},
{"learn":[0.07735616854],"iteration":310,"passed_time":1.66750803,"remaining_time":3.694254125},
{"learn":[0.07730780062],"iteration":311,"passed_time":1.672536884,"remaining_time":3.688158257},
{"learn":[0.07724014712],"iteration":312,"passed_time":1.67751652,"remaining_time":3.681961179},
{"learn":[0.07719914131],"iteration":313,"passed_time":1.682155046,"remaining_time":3.675026628},
{"learn":[0.07717786267],"iteration":314,"passed_time":1.686984191,"remaining_time":3.668521177},
{"learn":[0.0771704599],"iteration":315,"passed_time":1.691140086,"remaining_time":3.660569047},
{"learn":[0.07712681604],"iteration":316,"passed_time":1.695796341,"remaining_time":3.653718929},
{"learn":[0.07709278301],"iteration":317,"passed_time":1.700445909,"remaining_time":3.646868269},
{"learn":[0.07704264865],"iteration":318,"passed_time":1.704991341,"remaining_time":3.639809102},
{"learn":[0.07699478045],"iteration":319,"passed_time":1.709677624,"remaining_time":3.63306495},
{"learn":[0.07694744682],"iteration":320,"passed_time":1.714175264,"remaining_time":3.625934592},
{"learn":[0.07689437227],"iteration":321,"passed_time":1.719091925,"remaining_time":3.619702873},
{"learn":[0.0768570969],"iteration":322,"passed_time":1.723902689,"remaining_time":3.61325734},
{"learn":[0.07683933371],"iteration":323,"passed_time":1.728746727,"remaining_time":3.60689132},
{"learn":[0.07682361588],"iteration":324,"passed_time":1.73426095,"remaining_time":3.601926588},
{"learn":[0.07679466137],"iteration":325,"passed_time":1.739487979,"remaining_time":3.596364717},
{"learn":[0.07679155848],"iteration":326,"passed_time":1.743689335,"remaining_time":3.588693953},
{"learn":[0.07675523024],"iteration":327,"passed_time":1.749390894,"remaining_time":3.584117929},
{"learn":[0.07672606074],"iteration":328,"passed_time":1.754561098,"remaining_time":3.578451357},
{"learn":[0.07667866901],"iteration":329,"passed_time":1.759615405,"remaining_time":3.57255249},
{"learn":[0.07664972612],"iteration":330,"passed_time":1.764697847,"remaining_time":3.566715588},
{"learn":[0.07662366531],"iteration":331,"passed_time":1.769602382,"remaining_time":3.560525274},
{"learn":[0.0765442801],"iteration":332,"passed_time":1.774624378,"remaining_time":3.554577959},
{"learn":[0.07652595909],"iteration":333,"passed_time":1.779473587,"remaining_time":3.548291644},
{"learn":[0.0764994683],"iteration":334,"passed_time":1.784065162,"remaining_time":3.541502485},
{"learn":[0.07646525514],"iteration":335,"passed_time":1.788892925,"remaining_time":3.535193161},
{"learn":[0.07643539998],"iteration":336,"passed_time":1.79393305,"remaining_time":3.529310423},
{"learn":[0.07640421999],"iteration":337,"passed_time":1.799041842,"remaining_time":3.523567158},
{"learn":[0.07637485873],"iteration":338,"passed_time":1.803761615,"remaining_time":3.517069107},
{"learn":[0.0763480716],"iteration":339,"passed_time":1.810176641,"remaining_time":3.513872303},
{"learn":[0.07633468965],"iteration":340,"passed_time":1.815469437,"remaining_time":3.508487856},
{"learn":[0.07631418965],"iteration":341,"passed_time":1.820671305,"remaining_time":3.502929003},
{"learn":[0.07629800696],"iteration":342,"passed_time":1.825695529,"remaining_time":3.49703196},
{"learn":[0.07622844757],"iteration":343,"passed_time":1.830788575,"remaining_time":3.491271237},
{"learn":[0.07616728458],"iteration":344,"passed_time":1.835954501,"remaining_time":3.485652748},
{"learn":[0.07613890532],"iteration":345,"passed_time":1.841459129,"remaining_time":3.480677082},
{"learn":[0.07611817289],"iteration":346,"passed_time":1.847089224,"remaining_time":3.475934477},
{"learn":[0.07604966523],"iteration":347,"passed_time":1.852643413,"remaining_time":3.471044556},
{"learn":[0.07603266325],"iteration":348,"passed_time":1.858102304,"remaining_time":3.465973066},
{"learn":[0.07597008826],"iteration":349,"passed_time":1.863816454,"remaining_time":3.461373415},
{"learn":[0.07594149401],"iteration":350,"passed_time":1.869658187,"remaining_time":3.457003315},
{"learn":[0.07588322473],"iteration":351,"passed_time":1.874937057,"remaining_time":3.451588672},
{"learn":[0.07586733258],"iteration":352,"passed_time":1.880286498,"remaining_time":3.446304147},
{"learn":[0.07582753538],"iteration":353,"passed_time":1.885463701,"remaining_time":3.440704947},
{"learn":[0.07578690145],"iteration":354,"passed_time":1.890395295,"remaining_time":3.434661873},
{"learn":[0.07576125901],"iteration":355,"passed_time":1.895314205,"remaining_time":3.428602101},
{"learn":[0.07570165909],"iteration":356,"passed_time":1.900298097,"remaining_time":3.422665761},
{"learn":[0.07563952572],"iteration":357,"passed_time":1.905035129,"remaining_time":3.416292046},
{"learn":[0.07560362747],"iteration":358,"passed_time":1.910125151,"remaining_time":3.410557721},
{"learn":[0.07555095966],"iteration":359,"passed_time":1.915047095,"remaining_time":3.40452817},
{"learn":[0.07552663043],"iteration":360,"passed_time":1.920097103,"remaining_time":3.398731438},
{"learn":[0.07548059259],"iteration":361,"passed_time":1.925196286,"remaining_time":3.393025499},
{"learn":[0.07541963297],"iteration":362,"passed_time":1.9303359,"remaining_time":3.387393852},
{"learn":[0.07536515224],"iteration":363,"passed_time":1.935287663,"remaining_time":3.381436685},
{"learn":[0.07533362941],"iteration":364,"passed_time":1.940054794,"remaining_time":3.37516382},
{"learn":[0.07530082244],"iteration":365,"passed_time":1.944797148,"remaining_time":3.368856263},
{"learn":[0.07526328558],"iteration":366,"passed_time":1.949757398,"remaining_time":3.36293306},
{"learn":[0.07520606222],"iteration":367,"passed_time":1.954713504,"remaining_time":3.357007974},
{"learn":[0.07515512599],"iteration":368,"passed_time":1.95968521,"remaining_time":3.351114816},
{"learn":[0.07511579945],"iteration":369,"passed_time":1.964537364,"remaining_time":3.345023079},
{"learn":[0.07509793749],"iteration":370,"passed_time":1.969514987,"remaining_time":3.339150747},
{"learn":[0.07506238788],"iteration":371,"passed_time":1.974312599,"remaining_time":3.332979333},
{"learn":[0.07499209053],"iteration":372,"passed_time":1.979458527,"remaining_time":3.327400794},
{"learn":[0.0749473717],"iteration":373,"passed_time":1.984290038,"remaining_time":3.3212983},
{"learn":[0.07489773706],"iteration":374,"passed_time":1.988964343,"remaining_time":3.314940572},
{"learn":[0.07487097898],"iteration":375,"passed_time":1.994730262,"remaining_time":3.310403413},
{"learn":[0.07483666123],"iteration":376,"passed_time":1.99969647,"remaining_time":3.304538198},
{"learn":[0.0747824536],"iteration":377,"passed_time":2.004521038,"remaining_time":3.298444672},
{"learn":[0.07473238896],"iteration":378,"passed_time":2.009355119,"remaining_time":3.292373428},
{"learn":[0.07470563088],"iteration":379,"passed_time":2.014116664,"remaining_time":3.286190346},
{"learn":[0.07467525276],"iteration":380,"passed_time":2.018918203,"remaining_time":3.280079706},
{"learn":[0.07462309048],"iteration":381,"passed_time":2.023845702,"remaining_time":3.274179695},
{"learn":[0.07461114376],"iteration":382,"passed_time":2.02879981,"remaining_time":3.268327631},
{"learn":[0.07453514616],"iteration":383,"passed_time":2.033932641,"remaining_time":3.262766946},
{"learn":[0.07447107784],"iteration":384,"passed_time":2.039237367,"remaining_time":3.257483067},
{"learn":[0.07444978178],"iteration":385,"passed_time":2.044662822,"remaining_time":3.252391121},
{"learn":[0.07440877596],"iteration":386,"passed_time":2.050171471,"remaining_time":3.247429229},
{"learn":[0.0743496467],"iteration":387,"passed_time":2.055938125,"remaining_time":3.242871475},
{"learn":[0.07431188323],"iteration":388,"passed_time":2.061677664,"remaining_time":3.238264916},
{"learn":[0.07426697847],"iteration":389,"passed_time":2.067198066,"remaining_time":3.233309796},
{"learn":[0.0742243631],"iteration":390,"passed_time":2.072742866,"remaining_time":3.228389784},
{"learn":[0.07419549574],"iteration":391,"passed_time":2.079075149,"remaining_time":3.224687986},
{"learn":[0.07417321187],"iteration":392,"passed_time":2.085585294,"remaining_time":3.221247515},
{"learn":[0.07413013746],"iteration":393,"passed_time":2.091476351,"remaining_time":3.21683926},
{"learn":[0.07411203145],"iteration":394,"passed_time":2.096647818,"remaining_time":3.211321341},
{"learn":[0.07409089808],"iteration":395,"passed_time":2.101777287,"remaining_time":3.205741115},
{"learn":[0.07407427379],"iteration":396,"passed_time":2.106442597,"remaining_time":3.199458151},
{"learn":[0.07403629532],"iteration":397,"passed_time":2.111522907,"remaining_time":3.19381103},
{"learn":[0.07401832877],"iteration":398,"passed_time":2.116732405,"remaining_time":3.188361342},
{"learn":[0.07398692797],"iteration":399,"passed_time":2.122066133,"remaining_time":3.1830992},
{"learn":[0.07395885087],"iteration":400,"passed_time":2.127357076,"remaining_time":3.177772789},
{"learn":[0.07389793193],"iteration":401,"passed_time":2.132454486,"remaining_time":3.172158663},
{"learn":[0.07384499683],"iteration":402,"passed_time":2.137658426,"remaining_time":3.166704914},
{"learn":[0.07378232307],"iteration":403,"passed_time":2.143031963,"remaining_time":3.161502599},
{"learn":[0.07367531979],"iteration":404,"passed_time":2.148205977,"remaining_time":3.156006312},
{"learn":[0.07362813143],"iteration":405,"passed_time":2.153332825,"remaining_time":3.150442605},
{"learn":[0.07360064702],"iteration":406,"passed_time":2.157779995,"remaining_time":3.143890754},
{"learn":[0.07359239007],"iteration":407,"passed_time":2.162829443,"remaining_time":3.138223114},
{"learn":[0.0735659109],"iteration":408,"passed_time":2.16887109,"remaining_time":3.133992211},
{"learn":[0.07356024551],"iteration":409,"passed_time":2.174498763,"remaining_time":3.129156757},
{"learn":[0.07353658451],"iteration":410,"passed_time":2.180044372,"remaining_time":3.124199842},
{"learn":[0.07348551463],"iteration":411,"passed_time":2.185209224,"remaining_time":3.118696659},
{"learn":[0.07347510774],"iteration":412,"passed_time":2.190803968,"remaining_time":3.113806124},
{"learn":[0.07342368923],"iteration":413,"passed_time":2.19682519,"remaining_time":3.109515849},
{"learn":[0.07340060929],"iteration":414,"passed_time":2.202828467,"remaining_time":3.105191936},
{"learn":[0.07332550072],"iteration":415,"passed_time":2.209219866,"remaining_time":3.101404811},
{"learn":[0.07331414088],"iteration":416,"passed_time":2.214999509,"remaining_time":3.096749913},
{"learn":[0.07330091001],"iteration":417,"passed_time":2.219892741,"remaining_time":3.090855444},
{"learn":[0.07324645252],"iteration":418,"passed_time":2.225020418,"remaining_time":3.085290842},
{"learn":[0.07322157709],"iteration":419,"passed_time":2.230287866,"remaining_time":3.079921339},
{"learn":[0.07319785218],"iteration":420,"passed_time":2.235753236,"remaining_time":3.074824521},
{"learn":[0.07316043735],"iteration":421,"passed_time":2.240881499,"remaining_time":3.069264233},
{"learn":[0.0731491821],"iteration":422,"passed_time":2.246266674,"remaining_time":3.064056433},
{"learn":[0.07313263335],"iteration":423,"passed_time":2.251387455,"remaining_time":3.058488618},
{"learn":[0.07308072092],"iteration":424,"passed_time":2.256208346,"remaining_time":3.052517174},
{"learn":[0.07300069654],"iteration":425,"passed_time":2.261071014,"remaining_time":3.046607423},
{"learn":[0.07295178241],"iteration":426,"passed_time":2.266017278,"remaining_time":3.040814754},
{"learn":[0.07291771452],"iteration":427,"passed_time":2.27169456,"remaining_time":3.03600301},
{"learn":[0.07287731301],"iteration":428,"passed_time":2.276820704,"remaining_time":3.030453664},
{"learn":[0.0728563191],"iteration":429,"passed_time":2.28153996,"remaining_time":3.024366923},
{"learn":[0.07284051411],"iteration":430,"passed_time":2.286111619,"remaining_time":3.018091674},
{"learn":[0.07280691689],"iteration":431,"passed_time":2.291079683,"remaining_time":3.012345509},
{"learn":[0.07273914718],"iteration":432,"passed_time":2.295852898,"remaining_time":3.00634779},
{"learn":[0.0726941262],"iteration":433,"passed_time":2.30056065,"remaining_time":3.000270341},
{"learn":[0.07268328351],"iteration":434,"passed_time":2.304891629,"remaining_time":2.993709817},
{"learn":[0.07264959912],"iteration":435,"passed_time":2.309418313,"remaining_time":2.98741268},
{"learn":[0.0726357407],"iteration":436,"passed_time":2.313869652,"remaining_time":2.981026577},
{"learn":[0.07260101621],"iteration":437,"passed_time":2.318384878,"remaining_time":2.974731282},
{"learn":[0.07257854058],"iteration":438,"passed_time":2.323057686,"remaining_time":2.968645471},
{"learn":[0.07254937107],"iteration":439,"passed_time":2.328135545,"remaining_time":2.963081603},
{"learn":[0.07251161341],"iteration":440,"passed_time":2.332657572,"remaining_time":2.95681538},
{"learn":[0.072455128],"iteration":441,"passed_time":2.337137836,"remaining_time":2.950504327},
{"learn":[0.07244115918],"iteration":442,"passed_time":2.341982757,"remaining_time":2.944660036},
{"learn":[0.07241736453],"iteration":443,"passed_time":2.347386694,"remaining_time":2.939520274},
{"learn":[0.07238067604],"iteration":444,"passed_time":2.353094682,"remaining_time":2.934758536},
{"learn":[0.07233737501],"iteration":445,"passed_time":2.358580152,"remaining_time":2.929716153},
{"learn":[0.07231225553],"iteration":446,"passed_time":2.363229494,"remaining_time":2.923637383},
{"learn":[0.07229421344],"iteration":447,"passed_time":2.367773534,"remaining_time":2.917435248},
{"learn":[0.07222553146],"iteration":448,"passed_time":2.372620274,"remaining_time":2.911611962},
{"learn":[0.0722133988],"iteration":449,"passed_time":2.377205483,"remaining_time":2.905473368},
{"learn":[0.07219429336],"iteration":450,"passed_time":2.381870384,"remaining_time":2.899438672},
{"learn":[0.07217347958],"iteration":451,"passed_time":2.38641229,"remaining_time":2.893260918},
{"learn":[0.07212766254],"iteration":452,"passed_time":2.391051725,"remaining_time":2.887208153},
{"learn":[0.07207698778],"iteration":453,"passed_time":2.395788504,"remaining_time":2.881278686},
{"learn":[0.07204053752],"iteration":454,"passed_time":2.400436855,"remaining_time":2.875248541},
{"learn":[0.07203837596],"iteration":455,"passed_time":2.404724645,"remaining_time":2.868794313},
{"learn":[0.07201889863],"iteration":456,"passed_time":2.409634648,"remaining_time":2.863088871},
{"learn":[0.07201139707],"iteration":457,"passed_time":2.414262527,"remaining_time":2.857053034},
{"learn":[0.07197302348],"iteration":458,"passed_time":2.419201207,"remaining_time":2.851389658},
{"learn":[0.07193774698],"iteration":459,"passed_time":2.424131139,"remaining_time":2.845719163},
{"learn":[0.07190205791],"iteration":460,"passed_time":2.429131544,"remaining_time":2.840134278},
{"learn":[0.07188664224],"iteration":461,"passed_time":2.434032975,"remaining_time":2.834436668},
{"learn":[0.07186886743],"iteration":462,"passed_time":2.43869177,"remaining_time":2.828461081},
{"learn":[0.07183596167],"iteration":463,"passed_time":2.443591585,"remaining_time":2.82276959},
{"learn":[0.07181245175],"iteration":464,"passed_time":2.448739861,"remaining_time":2.817367367},
{"learn":[0.07179546138],"iteration":465,"passed_time":2.453619641,"remaining_time":2.811658559},
{"learn":[0.07176314831],"iteration":466,"passed_time":2.45846762,"remaining_time":2.805917005},
{"learn":[0.07172575672],"iteration":467,"passed_time":2.463629016,"remaining_time":2.800535548},
{"learn":[0.07169582021],"iteration":468,"passed_time":2.469370387,"remaining_time":2.795811675},
{"learn":[0.07162763795],"iteration":469,"passed_time":2.474974926,"remaining_time":2.790929172},
{"learn":[0.07159429639],"iteration":470,"passed_time":2.480745641,"remaining_time":2.786230243},
{"learn":[0.07157852045],"iteration":471,"passed_time":2.486106668,"remaining_time":2.781068476},
{"learn":[0.07154699763],"iteration":472,"passed_time":2.491326736,"remaining_time":2.775748815},
{"learn":[0.07151254042],"iteration":473,"passed_time":2.496707382,"remaining_time":2.77060777},
{"learn":[0.07147715351],"iteration":474,"passed_time":2.501998881,"remaining_time":2.765367184},
{"learn":[0.07146724053],"iteration":475,"passed_time":2.507027929,"remaining_time":2.759837468},
{"learn":[0.07145189458],"iteration":476,"passed_time":2.512253064,"remaining_time":2.754524848},
{"learn":[0.07141694347],"iteration":477,"passed_time":2.517228383,"remaining_time":2.748939782},
{"learn":[0.07137877907],"iteration":478,"passed_time":2.522132156,"remaining_time":2.743279443},
{"learn":[0.07133012061],"iteration":479,"passed_time":2.527426947,"remaining_time":2.738045859},
{"learn":[0.07129722066],"iteration":480,"passed_time":2.534509306,"remaining_time":2.73474081},
{"learn":[0.07126310048],"iteration":481,"passed_time":2.540521946,"remaining_time":2.730270473},
{"learn":[0.0712352558],"iteration":482,"passed_time":2.54551828,"remaining_time":2.724705902},
{"learn":[0.07117823],"iteration":483,"passed_time":2.550626926,"remaining_time":2.719263417},
{"learn":[0.0711636743],"iteration":484,"passed_time":2.555596854,"remaining_time":2.71367501},
{"learn":[0.07112868252],"iteration":485,"passed_time":2.560388422,"remaining_time":2.707900512},
{"learn":[0.07106402151],"iteration":486,"passed_time":2.565159156,"remaining_time":2.702108105},
{"learn":[0.07102446255],"iteration":487,"passed_time":2.570073454,"remaining_time":2.696470509},
{"learn":[0.07098181812],"iteration":488,"passed_time":2.575222376,"remaining_time":2.691081051},
{"learn":[0.07095472883],"iteration":489,"passed_time":2.58022222,"remaining_time":2.685537413},
{"learn":[0.07091858654],"iteration":490,"passed_time":2.585114269,"remaining_time":2.679884243},
{"learn":[0.07087262423],"iteration":491,"passed_time":2.590428371,"remaining_time":2.674669944},
{"learn":[0.0708567437],"iteration":492,"passed_time":2.595574042,"remaining_time":2.669282027},
{"learn":[0.07081877686],"iteration":493,"passed_time":2.601380514,"remaining_time":2.664571943},
{"learn":[0.0707603042],"iteration":494,"passed_time":2.606987446,"remaining_time":2.659653859},
{"learn":[0.07075017041],"iteration":495,"passed_time":2.612046703,"remaining_time":2.654176489},
{"learn":[0.0707312451],"iteration":496,"passed_time":2.617579711,"remaining_time":2.649180271},
{"learn":[0.07070038469],"iteration":497,"passed_time":2.623127426,"remaining_time":2.644196722},
{"learn":[0.07068173829],"iteration":498,"passed_time":2.628760942,"remaining_time":2.639297058},
{"learn":[0.07064883253],"iteration":499,"passed_time":2.634691621,"remaining_time":2.634691621},
{"learn":[0.07063014545],"iteration":500,"passed_time":2.639735557,"remaining_time":2.62919769},
{"learn":[0.07062208026],"iteration":501,"passed_time":2.644629995,"remaining_time":2.623557246},
{"learn":[0.0705987679],"iteration":502,"passed_time":2.6496882,"remaining_time":2.618081582},
{"learn":[0.07058553122],"iteration":503,"passed_time":2.654612624,"remaining_time":2.612475916},
{"learn":[0.07056677441],"iteration":504,"passed_time":2.659291341,"remaining_time":2.606632107},
{"learn":[0.07054840111],"iteration":505,"passed_time":2.664008542,"remaining_time":2.600830474},
{"learn":[0.07053554212],"iteration":506,"passed_time":2.668848458,"remaining_time":2.595152445},
{"learn":[0.07048767973],"iteration":507,"passed_time":2.673654398,"remaining_time":2.589444811},
{"learn":[0.07047816187],"iteration":508,"passed_time":2.678671436,"remaining_time":2.583944352},
{"learn":[0.07047146799],"iteration":509,"passed_time":2.683675413,"remaining_time":2.57843324},
{"learn":[0.07045533761],"iteration":510,"passed_time":2.688599427,"remaining_time":2.572847592},
{"learn":[0.07041489542],"iteration":511,"passed_time":2.693904204,"remaining_time":2.567627444},
{"learn":[0.07036765477],"iteration":512,"passed_time":2.698966915,"remaining_time":2.562177169},
{"learn":[0.07032831661],"iteration":513,"passed_time":2.704056694,"remaining_time":2.556753995},
{"learn":[0.07030214541],"iteration":514,"passed_time":2.710207725,"remaining_time":2.552331547},
{"learn":[0.07028695635],"iteration":515,"passed_time":2.715549523,"remaining_time":2.547143351},
{"learn":[0.07028179648],"iteration":516,"passed_time":2.720602695,"remaining_time":2.541684917},
{"learn":[0.07023724616],"iteration":517,"passed_time":2.725796551,"remaining_time":2.536358953},
{"learn":[0.07020699587],"iteration":518,"passed_time":2.730851228,"remaining_time":2.53090451},
{"learn":[0.07018453768],"iteration":519,"passed_time":2.735824532,"remaining_time":2.525376491},
{"learn":[0.07015912767],"iteration":520,"passed_time":2.740826789,"remaining_time":2.51987722},
{"learn":[0.07013371185],"iteration":521,"passed_time":2.745446842,"remaining_time":2.514029867},
{"learn":[0.0700697365],"iteration":522,"passed_time":2.750526432,"remaining_time":2.508606325},
{"learn":[0.07001327433],"iteration":523,"passed_time":2.755757899,"remaining_time":2.503322061},
{"learn":[0.0699840351],"iteration":524,"passed_time":2.760739343,"remaining_time":2.497811787},
{"learn":[0.06995501667],"iteration":525,"passed_time":2.765600972,"remaining_time":2.492195552},
{"learn":[0.06990690442],"iteration":526,"passed_time":2.770784902,"remaining_time":2.486871458},
{"learn":[0.06986991958],"iteration":527,"passed_time":2.775687741,"remaining_time":2.481296617},
{"learn":[0.0698347128],"iteration":528,"passed_time":2.780495308,"remaining_time":2.47563949},
{"learn":[0.06978794862],"iteration":529,"passed_time":2.785982693,"remaining_time":2.470588426},
{"learn":[0.069761115],"iteration":530,"passed_time":2.79120036,"remaining_time":2.465297493},
{"learn":[0.06972469379],"iteration":531,"passed_time":2.796568154,"remaining_time":2.460138903},
{"learn":[0.06970963257],"iteration":532,"passed_time":2.804270095,"remaining_time":2.457024642},
{"learn":[0.06967164829],"iteration":533,"passed_time":2.809415412,"remaining_time":2.451662139},
{"learn":[0.06962450642],"iteration":534,"passed_time":2.814351287,"remaining_time":2.446118408},
{"learn":[0.06959900344],"iteration":535,"passed_time":2.81961339,"remaining_time":2.440859353},
{"learn":[0.06954928745],"iteration":536,"passed_time":2.82474621,"remaining_time":2.435488818},
{"learn":[0.0695149174],"iteration":537,"passed_time":2.82990506,"remaining_time":2.43014152},
{"learn":[0.06950802596],"iteration":538,"passed_time":2.834840841,"remaining_time":2.424604133},
{"learn":[0.06946804863],"iteration":539,"passed_time":2.839996371,"remaining_time":2.419256168},
{"learn":[0.06941484624],"iteration":540,"passed_time":2.845345527,"remaining_time":2.414073192},
{"learn":[0.06935230031],"iteration":541,"passed_time":2.85074554,"remaining_time":2.408932578},
{"learn":[0.06932532143],"iteration":542,"passed_time":2.856388745,"remaining_time":2.403995684},
{"learn":[0.06930503642],"iteration":543,"passed_time":2.861795538,"remaining_time":2.398858024},
{"learn":[0.0692800041],"iteration":544,"passed_time":2.866946449,"remaining_time":2.393505751},
{"learn":[0.0692422232],"iteration":545,"passed_time":2.87206584,"remaining_time":2.388128006},
{"learn":[0.06921536634],"iteration":546,"passed_time":2.877965752,"remaining_time":2.383397597},
{"learn":[0.06918008402],"iteration":547,"passed_time":2.882830848,"remaining_time":2.377809386},
{"learn":[0.06915538872],"iteration":548,"passed_time":2.888141884,"remaining_time":2.372590145},
{"learn":[0.06910761349],"iteration":549,"passed_time":2.893651613,"remaining_time":2.367533138},
{"learn":[0.06908664282],"iteration":550,"passed_time":2.899190742,"remaining_time":2.362498445},
{"learn":[0.06906258088],"iteration":551,"passed_time":2.904988024,"remaining_time":2.35767144},
{"learn":[0.06905409732],"iteration":552,"passed_time":2.909652951,"remaining_time":2.351925622},
{"learn":[0.06901317867],"iteration":553,"passed_time":2.914592816,"remaining_time":2.346405047},
{"learn":[0.06898310851],"iteration":554,"passed_time":2.919396659,"remaining_time":2.340777501},
{"learn":[0.06895303835],"iteration":555,"passed_time":2.924291618,"remaining_time":2.33522568},
{"learn":[0.06893623974],"iteration":556,"passed_time":2.929115466,"remaining_time":2.329619661},
{"learn":[0.06889933625],"iteration":557,"passed_time":2.934350568,"remaining_time":2.324342206},
{"learn":[0.06888561728],"iteration":558,"passed_time":2.939309181,"remaining_time":2.318846778},
{"learn":[0.06885688358],"iteration":559,"passed_time":2.944527452,"remaining_time":2.313557284},
{"learn":[0.06880940469],"iteration":560,"passed_time":2.950484226,"remaining_time":2.308845945},
{"learn":[0.06879364037],"iteration":561,"passed_time":2.955778162,"remaining_time":2.303613585},
{"learn":[0.06873370343],"iteration":562,"passed_time":2.96110075,"remaining_time":2.298403247},
{"learn":[0.06869359245],"iteration":563,"passed_time":2.966802352,"remaining_time":2.293485506},
{"learn":[0.0686579092],"iteration":564,"passed_time":2.972072788,"remaining_time":2.288233031},
{"learn":[0.06864821121],"iteration":565,"passed_time":2.977247421,"remaining_time":2.282907033},
{"learn":[0.06860798983],"iteration":566,"passed_time":2.982894802,"remaining_time":2.277942591},
{"learn":[0.06860154],"iteration":567,"passed_time":2.988230389,"remaining_time":2.272738606},
{"learn":[0.06856388693],"iteration":568,"passed_time":2.993535446,"remaining_time":2.267511032},
{"learn":[0.06852215479],"iteration":569,"passed_time":2.998989114,"remaining_time":2.262395297},
{"learn":[0.06849329325],"iteration":570,"passed_time":3.004209685,"remaining_time":2.257103249},
{"learn":[0.06844849888],"iteration":571,"passed_time":3.009793569,"remaining_time":2.2520833},
{"learn":[0.06843620353],"iteration":572,"passed_time":3.015444444,"remaining_time":2.247111305},
{"learn":[0.06841685984],"iteration":573,"passed_time":3.020688443,"remaining_time":2.241834977},
{"learn":[0.06838731265],"iteration":574,"passed_time":3.026303135,"remaining_time":2.236832752},
{"learn":[0.06834864852],"iteration":575,"passed_time":3.032043965,"remaining_time":2.231921252},
{"learn":[0.06832182653],"iteration":576,"passed_time":3.037486188,"remaining_time":2.226787968},
{"learn":[0.06829273837],"iteration":577,"passed_time":3.0435153,"remaining_time":2.222082105},
{"learn":[0.06827019882],"iteration":578,"passed_time":3.048823901,"remaining_time":2.216847776},
{"learn":[0.06822016906],"iteration":579,"passed_time":3.05482078,"remaining_time":2.212111599},
{"learn":[0.06817662979],"iteration":580,"passed_time":3.060637789,"remaining_time":2.207241366},
{"learn":[0.06817325961],"iteration":581,"passed_time":3.066166836,"remaining_time":2.202161061},
{"learn":[0.06815789623],"iteration":582,"passed_time":3.071412362,"remaining_time":2.196876424},
{"learn":[0.06813609464],"iteration":583,"passed_time":3.076460036,"remaining_time":2.191450984},
{"learn":[0.06809417655],"iteration":584,"passed_time":3.081495234,"remaining_time":2.186017987},
{"learn":[0.068053316],"iteration":585,"passed_time":3.086585028,"remaining_time":2.180624918},
{"learn":[0.06804044539],"iteration":586,"passed_time":3.091345511,"remaining_time":2.175001186},
{"learn":[0.06800033442],"iteration":587,"passed_time":3.09596694,"remaining_time":2.169282958},
{"learn":[0.06799141505],"iteration":588,"passed_time":3.100807288,"remaining_time":2.163721215},
{"learn":[0.06795886956],"iteration":589,"passed_time":3.10552255,"remaining_time":2.158074993},
{"learn":[0.06792505152],"iteration":590,"passed_time":3.110144463,"remaining_time":2.152367319},
{"learn":[0.06791134418],"iteration":591,"passed_time":3.114654212,"remaining_time":2.146586011},
{"learn":[0.06787686954],"iteration":592,"passed_time":3.119288616,"remaining_time":2.140894548},
{"learn":[0.06786505067],"iteration":593,"passed_time":3.123645783,"remaining_time":2.135017151},
{"learn":[0.06783184856],"iteration":594,"passed_time":3.128069333,"remaining_time":2.12919005},
{"learn":[0.06779002344],"iteration":595,"passed_time":3.132489543,"remaining_time":2.123365395},
{"learn":[0.06774990666],"iteration":596,"passed_time":3.137158551,"remaining_time":2.117713394},
{"learn":[0.0677186395],"iteration":597,"passed_time":3.142005874,"remaining_time":2.112184551},
{"learn":[0.06770121915],"iteration":598,"passed_time":3.146887337,"remaining_time":2.106680838},
{"learn":[0.06767551861],"iteration":599,"passed_time":3.151720952,"remaining_time":2.101147302},
{"learn":[0.06763232217],"iteration":600,"passed_time":3.156905992,"remaining_time":2.095849402},
{"learn":[0.06759816131],"iteration":601,"passed_time":3.162856092,"remaining_time":2.091057682},
{"learn":[0.06757759739],"iteration":602,"passed_time":3.168897284,"remaining_time":2.086322092},
{"learn":[0.06754510419],"iteration":603,"passed_time":3.175290496,"remaining_time":2.081812974},
{"learn":[0.06750772422],"iteration":604,"passed_time":3.180875407,"remaining_time":2.076769894},
{"learn":[0.06746853133],"iteration":605,"passed_time":3.18628692,"remaining_time":2.071612288},
{"learn":[0.06743737458],"iteration":606,"passed_time":3.191602795,"remaining_time":2.066391925},
{"learn":[0.06741807158],"iteration":607,"passed_time":3.196781967,"remaining_time":2.061083111},
{"learn":[0.06740656066],"iteration":608,"passed_time":3.201946547,"remaining_time":2.055765353},
{"learn":[0.06737164441],"iteration":609,"passed_time":3.207120594,"remaining_time":2.050454151},
{"learn":[0.06733784962],"iteration":610,"passed_time":3.212688408,"remaining_time":2.045394093},
{"learn":[0.06730633261],"iteration":611,"passed_time":3.217602057,"remaining_time":2.039917644},
{"learn":[0.06728235203],"iteration":612,"passed_time":3.222827277,"remaining_time":2.034639733},
{"learn":[0.06727391495],"iteration":613,"passed_time":3.227629289,"remaining_time":2.029095937},
{"learn":[0.06727114327],"iteration":614,"passed_time":3.232170506,"remaining_time":2.023391292},
{"learn":[0.06725174729],"iteration":615,"passed_time":3.237574045,"remaining_time":2.018227976},
{"learn":[0.06721913787],"iteration":616,"passed_time":3.242523893,"remaining_time":2.012782255},
{"learn":[0.06719190913],"iteration":617,"passed_time":3.247423519,"remaining_time":2.007307094},
{"learn":[0.06716172857],"iteration":618,"passed_time":3.252042048,"remaining_time":2.001660776},
{"learn":[0.06713523778],"iteration":619,"passed_time":3.256902859,"remaining_time":1.996166268},
{"learn":[0.06712436603],"iteration":620,"passed_time":3.261773582,"remaining_time":1.990679851},
{"learn":[0.06711827065],"iteration":621,"passed_time":3.266339948,"remaining_time":1.985010451},
{"learn":[0.06709577759],"iteration":622,"passed_time":3.270999572,"remaining_time":1.979401025},
{"learn":[0.06708147175],"iteration":623,"passed_time":3.275578766,"remaining_time":1.973746179},
{"learn":[0.06706253482],"iteration":624,"passed_time":3.28032031,"remaining_time":1.968192186},
{"learn":[0.06703395219],"iteration":625,"passed_time":3.285700767,"remaining_time":1.963022503},
{"learn":[0.06700647358],"iteration":626,"passed_time":3.29136355,"remaining_time":1.958020102},
{"learn":[0.06700083725],"iteration":627,"passed_time":3.297576571,"remaining_time":1.953341536},
{"learn":[0.06697656613],"iteration":628,"passed_time":3.30355526,"remaining_time":1.948519875},
{"learn":[0.06695814634],"iteration":629,"passed_time":3.309493733,"remaining_time":1.943670922},
{"learn":[0.06693154514],"iteration":630,"passed_time":3.315502672,"remaining_time":1.938859724},
{"learn":[0.06692451425],"iteration":631,"passed_time":3.321405861,"remaining_time":1.93398316},
{"learn":[0.06690689052],"iteration":632,"passed_time":3.32687255,"remaining_time":1.928850278},
{"learn":[0.06689702983],"iteration":633,"passed_time":3.332469065,"remaining_time":1.92379129},
{"learn":[0.06687135834],"iteration":634,"passed_time":3.338114668,"remaining_time":1.918758825},
{"learn":[0.06685919083],"iteration":635,"passed_time":3.343622463,"remaining_time":1.913645561},
{"learn":[0.06683429796],"iteration":636,"passed_time":3.349056625,"remaining_time":1.908489097},
{"learn":[0.06681652316],"iteration":637,"passed_time":3.354127804,"remaining_time":1.903125807},
{"learn":[0.06677988115],"iteration":638,"passed_time":3.359381864,"remaining_time":1.897866749},
{"learn":[0.06674964829],"iteration":639,"passed_time":3.364693811,"remaining_time":1.892640269},
{"learn":[0.06672673106],"iteration":640,"passed_time":3.369881621,"remaining_time":1.887343997},
{"learn":[0.06671354667],"iteration":641,"passed_time":3.375004914,"remaining_time":1.882012086},
{"learn":[0.0666588277],"iteration":642,"passed_time":3.380127876,"remaining_time":1.87668064},
{"learn":[0.06663509116],"iteration":643,"passed_time":3.384950701,"remaining_time":1.871183928},
{"learn":[0.06663226718],"iteration":644,"passed_time":3.389749101,"remaining_time":1.865675862},
{"learn":[0.06661534073],"iteration":645,"passed_time":3.394403366,"remaining_time":1.860091009},
{"learn":[0.06659457344],"iteration":646,"passed_time":3.399204245,"remaining_time":1.854589024},
{"learn":[0.0665592795],"iteration":647,"passed_time":3.404219436,"remaining_time":1.84920562},
{"learn":[0.06654514798],"iteration":648,"passed_time":3.409219565,"remaining_time":1.843815204},
{"learn":[0.06652052822],"iteration":649,"passed_time":3.413906259,"remaining_time":1.838257217},
{"learn":[0.06648586183],"iteration":650,"passed_time":3.419126412,"remaining_time":1.832987892},
{"learn":[0.06645784284],"iteration":651,"passed_time":3.423749059,"remaining_time":1.827399805},
{"learn":[0.06643392036],"iteration":652,"passed_time":3.428978871,"remaining_time":1.822137317},
{"learn":[0.06638140362],"iteration":653,"passed_time":3.434931922,"remaining_time":1.817257561},
{"learn":[0.06632932269],"iteration":654,"passed_time":3.440786278,"remaining_time":1.812322544},
{"learn":[0.06632667884],"iteration":655,"passed_time":3.445087846,"remaining_time":1.806570456},
{"learn":[0.06630439497],"iteration":656,"passed_time":3.449648493,"remaining_time":1.800958041},
{"learn":[0.06628288972],"iteration":657,"passed_time":3.4542275,"remaining_time":1.795358366},
{"learn":[0.06623215105],"iteration":658,"passed_time":3.45912897,"remaining_time":1.789928647},
{"learn":[0.06621750819],"iteration":659,"passed_time":3.463922482,"remaining_time":1.784444915},
{"learn":[0.06618832707],"iteration":660,"passed_time":3.469374443,"remaining_time":1.779300963},
{"learn":[0.06617520079],"iteration":661,"passed_time":3.474283311,"remaining_time":1.77387879},
{"learn":[0.0661259264],"iteration":662,"passed_time":3.479224606,"remaining_time":1.768474649},
{"learn":[0.06610261404],"iteration":663,"passed_time":3.484809146,"remaining_time":1.763397399},
{"learn":[0.06607656486],"iteration":664,"passed_time":3.491359009,"remaining_time":1.758804914},
{"learn":[0.06606070176],"iteration":665,"passed_time":3.498394881,"remaining_time":1.754450286},
{"learn":[0.06605367668],"iteration":666,"passed_time":3.503792816,"remaining_time":1.749269877},
{"learn":[0.06600127616],"iteration":667,"passed_time":3.508832052,"remaining_time":1.743910541},
{"learn":[0.06595251311],"iteration":668,"passed_time":3.514264936,"remaining_time":1.738746927},
{"learn":[0.06594705691],"iteration":669,"passed_time":3.519394404,"remaining_time":1.733433065},
{"learn":[0.06592132731],"iteration":670,"passed_time":3.524717104,"remaining_time":1.728214497},
{"learn":[0.06590970018],"iteration":671,"passed_time":3.530194265,"remaining_time":1.72307101},
{"learn":[0.06586281398],"iteration":672,"passed_time":3.535773321,"remaining_time":1.717976042},
{"learn":[0.06583807801],"iteration":673,"passed_time":3.54144442,"remaining_time":1.712924156},
{"learn":[0.0658119591],"iteration":674,"passed_time":3.546930371,"remaining_time":1.70778129},
{"learn":[0.06576684515],"iteration":675,"passed_time":3.552554934,"remaining_time":1.702703844},
{"learn":[0.06574420101],"iteration":676,"passed_time":3.557878015,"remaining_time":1.697480944},
{"learn":[0.0657315454],"iteration":677,"passed_time":3.562911502,"remaining_time":1.692120212},
{"learn":[0.06571194023],"iteration":678,"passed_time":3.568247372,"remaining_time":1.686903397},
{"learn":[0.06570950557],"iteration":679,"passed_time":3.57322987,"remaining_time":1.681519939},
{"learn":[0.06569499054],"iteration":680,"passed_time":3.578227491,"remaining_time":1.676144743},
{"learn":[0.06568938907],"iteration":681,"passed_time":3.583249973,"remaining_time":1.670782245},
{"learn":[0.06567739587],"iteration":682,"passed_time":3.588457228,"remaining_time":1.665506503},
{"learn":[0.06565590805],"iteration":683,"passed_time":3.593576877,"remaining_time":1.660190487},
{"learn":[0.06563560561],"iteration":684,"passed_time":3.598892207,"remaining_time":1.654965029},
{"learn":[0.06562190408],"iteration":685,"passed_time":3.604460939,"remaining_time":1.649855299},
{"learn":[0.06557895169],"iteration":686,"passed_time":3.610127206,"remaining_time":1.644788669},
{"learn":[0.06556574988],"iteration":687,"passed_time":3.614910571,"remaining_time":1.63931991},
{"learn":[0.0655383933],"iteration":688,"passed_time":3.619974554,"remaining_time":1.633979806},
{"learn":[0.06551109482],"iteration":689,"passed_time":3.624870961,"remaining_time":1.628565214},
{"learn":[0.06549049604],"iteration":690,"passed_time":3.6295271,"remaining_time":1.62304468},
{"learn":[0.06547890378],"iteration":691,"passed_time":3.634479769,"remaining_time":1.617658626},
{"learn":[0.06545907781],"iteration":692,"passed_time":3.6401455,"remaining_time":1.612589709},
{"learn":[0.06544719501],"iteration":693,"passed_time":3.645447157,"remaining_time":1.607358545},
{"learn":[0.06544105896],"iteration":694,"passed_time":3.650332488,"remaining_time":1.601944473},
{"learn":[0.0654291994],"iteration":695,"passed_time":3.654876656,"remaining_time":1.596382907},
{"learn":[0.06540970465],"iteration":696,"passed_time":3.659487736,"remaining_time":1.590853349},
{"learn":[0.06539066312],"iteration":697,"passed_time":3.664538277,"remaining_time":1.585516561},
{"learn":[0.06537115093],"iteration":698,"passed_time":3.670237556,"remaining_time":1.580459949},
{"learn":[0.06535245223],"iteration":699,"passed_time":3.675491142,"remaining_time":1.575210489},
{"learn":[0.06534429987],"iteration":700,"passed_time":3.68151877,"remaining_time":1.570291173},
{"learn":[0.0653222891],"iteration":701,"passed_time":3.686696281,"remaining_time":1.565007823},
{"learn":[0.06530762881],"iteration":702,"passed_time":3.692031056,"remaining_time":1.559791214},
{"learn":[0.06529633289],"iteration":703,"passed_time":3.697347631,"remaining_time":1.554566618},
{"learn":[0.06528540885],"iteration":704,"passed_time":3.70362779,"remaining_time":1.549744962},
{"learn":[0.06526243351],"iteration":705,"passed_time":3.709372314,"remaining_time":1.54469612},
{"learn":[0.06525135839],"iteration":706,"passed_time":3.714111648,"remaining_time":1.539228731},
{"learn":[0.06523870278],"iteration":707,"passed_time":3.718816204,"remaining_time":1.533749056},
{"learn":[0.06522826684],"iteration":708,"passed_time":3.723528786,"remaining_time":1.528274862},
{"learn":[0.06521041068],"iteration":709,"passed_time":3.728079422,"remaining_time":1.522736665},
{"learn":[0.06516138035],"iteration":710,"passed_time":3.732546051,"remaining_time":1.517167101},
{"learn":[0.06515149061],"iteration":711,"passed_time":3.7370655,"remaining_time":1.511622},
{"learn":[0.06513511036],"iteration":712,"passed_time":3.74178913,"remaining_time":1.506161964},
{"learn":[0.06511780622],"iteration":713,"passed_time":3.746300409,"remaining_time":1.500618931},
{"learn":[0.06510014182],"iteration":714,"passed_time":3.750921923,"remaining_time":1.495122724},
{"learn":[0.06505340088],"iteration":715,"passed_time":3.75575572,"remaining_time":1.489713163},
{"learn":[0.0650413089],"iteration":716,"passed_time":3.760793112,"remaining_time":1.484385566},
{"learn":[0.06503507406],"iteration":717,"passed_time":3.765773408,"remaining_time":1.479036352},
{"learn":[0.06501787452],"iteration":718,"passed_time":3.770920639,"remaining_time":1.473753407},
{"learn":[0.06499503863],"iteration":719,"passed_time":3.775943575,"remaining_time":1.468422502},
{"learn":[0.06495051736],"iteration":720,"passed_time":3.781138319,"remaining_time":1.463158933},
{"learn":[0.06494102275],"iteration":721,"passed_time":3.786308672,"remaining_time":1.457886165},
{"learn":[0.06493900645],"iteration":722,"passed_time":3.791020138,"remaining_time":1.452437868},
{"learn":[0.06489353805],"iteration":723,"passed_time":3.796020736,"remaining_time":1.447101828},
{"learn":[0.06487173646],"iteration":724,"passed_time":3.801776945,"remaining_time":1.442053324},
{"learn":[0.06482903974],"iteration":725,"passed_time":3.807073895,"remaining_time":1.436829542},
{"learn":[0.06480298474],"iteration":726,"passed_time":3.812106186,"remaining_time":1.431506174},
{"learn":[0.06478805716],"iteration":727,"passed_time":3.816947459,"remaining_time":1.426112237},
{"learn":[0.06475534897],"iteration":728,"passed_time":3.821804608,"remaining_time":1.420725718},
{"learn":[0.06473916047],"iteration":729,"passed_time":3.826512169,"remaining_time":1.415285323},
{"learn":[0.06472002597],"iteration":730,"passed_time":3.831132113,"remaining_time":1.40981469},
{"learn":[0.06470125174],"iteration":731,"passed_time":3.836769988,"remaining_time":1.404719067},
{"learn":[0.06468778263],"iteration":732,"passed_time":3.841464736,"remaining_time":1.399278424},
{"learn":[0.06467354652],"iteration":733,"passed_time":3.845937688,"remaining_time":1.393759435},
{"learn":[0.06465268044],"iteration":734,"passed_time":3.850386055,"remaining_time":1.388234428},
{"learn":[0.06465097792],"iteration":735,"passed_time":3.855040638,"remaining_time":1.382786316},
{"learn":[0.06463512063],"iteration":736,"passed_time":3.859893234,"remaining_time":1.377411018},
{"learn":[0.0645941032],"iteration":737,"passed_time":3.864544319,"remaining_time":1.371965598},
{"learn":[0.0645784609],"iteration":738,"passed_time":3.869514525,"remaining_time":1.366635035},
{"learn":[0.06456718823],"iteration":739,"passed_time":3.875497816,"remaining_time":1.361661395},
{"learn":[0.06455640945],"iteration":740,"passed_time":3.881413747,"remaining_time":1.356661485},
{"learn":[0.06454458476],"iteration":741,"passed_time":3.887351602,"remaining_time":1.35166673},
{"learn":[0.06453629876],"iteration":742,"passed_time":3.893341616,"remaining_time":1.346687477},
{"learn":[0.06452039499],"iteration":743,"passed_time":3.898948027,"remaining_time":1.341573515},
{"learn":[0.06451869247],"iteration":744,"passed_time":3.904494065,"remaining_time":1.336437566},
{"learn":[0.06450928501],"iteration":745,"passed_time":3.909905763,"remaining_time":1.331254777},
{"learn":[0.06450765803],"iteration":746,"passed_time":3.915062669,"remaining_time":1.325985081},
{"learn":[0.0644949385],"iteration":747,"passed_time":3.92065353,"remaining_time":1.320861884},
{"learn":[0.06448053969],"iteration":748,"passed_time":3.925902977,"remaining_time":1.315623027},
{"learn":[0.06447435134],"iteration":749,"passed_time":3.931185897,"remaining_time":1.310395299},
{"learn":[0.06446549008],"iteration":750,"passed_time":3.936458286,"remaining_time":1.305163932},
{"learn":[0.06445033588],"iteration":751,"passed_time":3.941409244,"remaining_time":1.299826453},
{"learn":[0.06444000453],"iteration":752,"passed_time":3.946388041,"remaining_time":1.294499132},
{"learn":[0.06443098058],"iteration":753,"passed_time":3.951693915,"remaining_time":1.289279447},
{"learn":[0.06442199149],"iteration":754,"passed_time":3.956766557,"remaining_time":1.28398385},
{"learn":[0.06440581462],"iteration":755,"passed_time":3.961774941,"remaining_time":1.278668103},
{"learn":[0.06438902763],"iteration":756,"passed_time":3.96711901,"remaining_time":1.273460924},
{"learn":[0.06436528528],"iteration":757,"passed_time":3.973674554,"remaining_time":1.268640161},
{"learn":[0.06435717941],"iteration":758,"passed_time":3.978846489,"remaining_time":1.263375499},
{"learn":[0.06434304208],"iteration":759,"passed_time":3.984691685,"remaining_time":1.25832369},
{"learn":[0.06433450041],"iteration":760,"passed_time":3.989743462,"remaining_time":1.253020614},
{"learn":[0.06432582509],"iteration":761,"passed_time":3.994953472,"remaining_time":1.24776762},
{"learn":[0.06431097886],"iteration":762,"passed_time":4.00066724,"remaining_time":1.242671214},
{"learn":[0.06430265219],"iteration":763,"passed_time":4.005708239,"remaining_time":1.237365372},
{"learn":[0.06428846256],"iteration":764,"passed_time":4.011153416,"remaining_time":1.232184383},
{"learn":[0.06427237866],"iteration":765,"passed_time":4.01654316,"remaining_time":1.226985769},
{"learn":[0.06426251216],"iteration":766,"passed_time":4.022055441,"remaining_time":1.221823882},
{"learn":[0.06424548693],"iteration":767,"passed_time":4.027662466,"remaining_time":1.216689703},
{"learn":[0.06420344682],"iteration":768,"passed_time":4.033198735,"remaining_time":1.21153304},
{"learn":[0.06419505042],"iteration":769,"passed_time":4.038538759,"remaining_time":1.206316772},
{"learn":[0.06418721765],"iteration":770,"passed_time":4.04407956,"remaining_time":1.201159817},
{"learn":[0.06418570688],"iteration":771,"passed_time":4.049220466,"remaining_time":1.195883765},
{"learn":[0.06417246439],"iteration":772,"passed_time":4.054376458,"remaining_time":1.190612491},
{"learn":[0.06416485242],"iteration":773,"passed_time":4.05970153,"remaining_time":1.185390886},
{"learn":[0.06414600846],"iteration":774,"passed_time":4.064758267,"remaining_time":1.18009111},
{"learn":[0.064122208],"iteration":775,"passed_time":4.069961658,"remaining_time":1.174834293},
{"learn":[0.06411785001],"iteration":776,"passed_time":4.075478017,"remaining_time":1.169667436},
{"learn":[0.06407803538],"iteration":777,"passed_time":4.080748758,"remaining_time":1.164429594},
{"learn":[0.06405503679],"iteration":778,"passed_time":4.085894433,"remaining_time":1.159156187},
{"learn":[0.06404711105],"iteration":779,"passed_time":4.090974906,"remaining_time":1.153864717},
{"learn":[0.06403888897],"iteration":780,"passed_time":4.09602766,"remaining_time":1.148566015},
{"learn":[0.06403163146],"iteration":781,"passed_time":4.101143051,"remaining_time":1.143285403},
{"learn":[0.06401196819],"iteration":782,"passed_time":4.106461003,"remaining_time":1.138061351},
{"learn":[0.06396687167],"iteration":783,"passed_time":4.111928105,"remaining_time":1.132878151},
{"learn":[0.06394451807],"iteration":784,"passed_time":4.117396485,"remaining_time":1.127694579},
{"learn":[0.06390714391],"iteration":785,"passed_time":4.122885819,"remaining_time":1.122515986},
{"learn":[0.06387097256],"iteration":786,"passed_time":4.12863235,"remaining_time":1.117406214},
{"learn":[0.06385690496],"iteration":787,"passed_time":4.13451367,"remaining_time":1.112331089},
{"learn":[0.0638266721],"iteration":788,"passed_time":4.140526778,"remaining_time":1.107289164},
{"learn":[0.06381349934],"iteration":789,"passed_time":4.146382292,"remaining_time":1.102202888},
{"learn":[0.06380623602],"iteration":790,"passed_time":4.152373466,"remaining_time":1.097150511},
{"learn":[0.06379847298],"iteration":791,"passed_time":4.158154238,"remaining_time":1.092040507},
{"learn":[0.06378148261],"iteration":792,"passed_time":4.164554213,"remaining_time":1.087090444},
{"learn":[0.06377423091],"iteration":793,"passed_time":4.170210883,"remaining_time":1.081943882},
{"learn":[0.06376099423],"iteration":794,"passed_time":4.175835698,"remaining_time":1.076787822},
{"learn":[0.06373913453],"iteration":795,"passed_time":4.182090038,"remaining_time":1.071791919},
{"learn":[0.06370436355],"iteration":796,"passed_time":4.18822101,"remaining_time":1.066761437},
{"learn":[0.06369389275],"iteration":797,"passed_time":4.193973175,"remaining_time":1.061632308},
{"learn":[0.06365543781],"iteration":798,"passed_time":4.199874081,"remaining_time":1.056539037},
{"learn":[0.06362568724],"iteration":799,"passed_time":4.205359058,"remaining_time":1.051339764},
{"learn":[0.06359648287],"iteration":800,"passed_time":4.210804539,"remaining_time":1.046129967},
{"learn":[0.06358294403],"iteration":801,"passed_time":4.216163747,"remaining_time":1.040898282},
{"learn":[0.06355520395],"iteration":802,"passed_time":4.222443843,"remaining_time":1.035892201},
{"learn":[0.06355092731],"iteration":803,"passed_time":4.227646155,"remaining_time":1.030620207},
{"learn":[0.06353432044],"iteration":804,"passed_time":4.232815395,"remaining_time":1.025340375},
{"learn":[0.06352144403],"iteration":805,"passed_time":4.238687209,"remaining_time":1.020229924},
{"learn":[0.06351476758],"iteration":806,"passed_time":4.244636339,"remaining_time":1.015136076},
{"learn":[0.06350562741],"iteration":807,"passed_time":4.250034647,"remaining_time":1.009909223},
{"learn":[0.06346390689],"iteration":808,"passed_time":4.255214498,"remaining_time":1.00463037},
{"learn":[0.06342721839],"iteration":809,"passed_time":4.26022541,"remaining_time":0.9993121332},
{"learn":[0.06341505668],"iteration":810,"passed_time":4.265143311,"remaining_time":0.9939729788},
{"learn":[0.06340223256],"iteration":811,"passed_time":4.270051123,"remaining_time":0.988632526},
{"learn":[0.06339357468],"iteration":812,"passed_time":4.274945349,"remaining_time":0.9832900126},
{"learn":[0.06338703769],"iteration":813,"passed_time":4.279548663,"remaining_time":0.9778821268},
{"learn":[0.06338024503],"iteration":814,"passed_time":4.284107355,"remaining_time":0.9724660868},
{"learn":[0.06336451557],"iteration":815,"passed_time":4.288679654,"remaining_time":0.9670552161},
{"learn":[0.06333478824],"iteration":816,"passed_time":4.293341647,"remaining_time":0.9616664889},
{"learn":[0.06332628725],"iteration":817,"passed_time":4.298069787,"remaining_time":0.9562942557},
{"learn":[0.06328615303],"iteration":818,"passed_time":4.302732318,"remaining_time":0.950909096},
{"learn":[0.06325533911],"iteration":819,"passed_time":4.307658398,"remaining_time":0.9455835508},
{"learn":[0.06324358996],"iteration":820,"passed_time":4.31247686,"remaining_time":0.9402355151},
{"learn":[0.06320117215],"iteration":821,"passed_time":4.317446857,"remaining_time":0.9349215821},
{"learn":[0.06318880707],"iteration":822,"passed_time":4.322577391,"remaining_time":0.9296430112},
{"learn":[0.06318018406],"iteration":823,"passed_time":4.328378352,"remaining_time":0.9245079976},
{"learn":[0.06317202589],"iteration":824,"passed_time":4.334274111,"remaining_time":0.9193914781},
{"learn":[0.06316539012],"iteration":825,"passed_time":4.340266936,"remaining_time":0.9142935191},
{"learn":[0.06315895191],"iteration":826,"passed_time":4.346407397,"remaining_time":0.9092242801},
{"learn":[0.06315307733],"iteration":827,"passed_time":4.352152366,"remaining_time":0.9040702982},
{"learn":[0.0631378476],"iteration":828,"passed_time":4.357908128,"remaining_time":0.8989171168},
{"learn":[0.06313240882],"iteration":829,"passed_time":4.363581701,"remaining_time":0.8937456496},
{"learn":[0.06313071211],"iteration":830,"passed_time":4.368863898,"remaining_time":0.88849338},
{"learn":[0.06310351242],"iteration":831,"passed_time":4.374539728,"remaining_time":0.8833205221},
{"learn":[0.06306599881],"iteration":832,"passed_time":4.380065165,"remaining_time":0.8781163057},
{"learn":[0.06305819509],"iteration":833,"passed_time":4.386311416,"remaining_time":0.8730547902},
{"learn":[0.06304621351],"iteration":834,"passed_time":4.392475094,"remaining_time":0.8679741203},
{"learn":[0.06303809602],"iteration":835,"passed_time":4.397564572,"remaining_time":0.8626801314},
{"learn":[0.06302089648],"iteration":836,"passed_time":4.402733118,"remaining_time":0.857402029},
{"learn":[0.06301284871],"iteration":837,"passed_time":4.40782312,"remaining_time":0.8521090041},
{"learn":[0.06297529443],"iteration":838,"passed_time":4.4131411,"remaining_time":0.8468602111},
{"learn":[0.06295933836],"iteration":839,"passed_time":4.419921112,"remaining_time":0.8418897356},
{"learn":[0.06294448632],"iteration":840,"passed_time":4.4252073,"remaining_time":0.8366325336},
{"learn":[0.06291984913],"iteration":841,"passed_time":4.430292646,"remaining_time":0.831337575},
{"learn":[0.06291401522],"iteration":842,"passed_time":4.435286095,"remaining_time":0.8260259987},
{"learn":[0.06290236485],"iteration":843,"passed_time":4.440789534,"remaining_time":0.8208094399},
{"learn":[0.06287331156],"iteration":844,"passed_time":4.445692903,"remaining_time":0.8154821302},
{"learn":[0.06284564121],"iteration":845,"passed_time":4.452642948,"remaining_time":0.8105283853},
{"learn":[0.06283735521],"iteration":846,"passed_time":4.462623229,"remaining_time":0.8061173012},
{"learn":[0.06283161428],"iteration":847,"passed_time":4.470455522,"remaining_time":0.8013080653},
{"learn":[0.06280302584],"iteration":848,"passed_time":4.476259484,"remaining_time":0.7961309565},
{"learn":[0.06277591331],"iteration":849,"passed_time":4.481686306,"remaining_time":0.7908858187},
{"learn":[0.06277041642],"iteration":850,"passed_time":4.486895791,"remaining_time":0.7856022008},
{"learn":[0.062743362],"iteration":851,"passed_time":4.492527637,"remaining_time":0.7803921248},
{"learn":[0.06273559896],"iteration":852,"passed_time":4.497271097,"remaining_time":0.7750279617},
{"learn":[0.06271224592],"iteration":853,"passed_time":4.501944418,"remaining_time":0.7696532611},
{"learn":[0.06268603985],"iteration":854,"passed_time":4.507411131,"remaining_time":0.7644147531},
{"learn":[0.06268068823],"iteration":855,"passed_time":4.512684098,"remaining_time":0.7591431193},
{"learn":[0.06266661482],"iteration":856,"passed_time":4.517525477,"remaining_time":0.7537994669},
{"learn":[0.06266512148],"iteration":857,"passed_time":4.521849379,"remaining_time":0.7483713424},
{"learn":[0.06263826462],"iteration":858,"passed_time":4.526608892,"remaining_time":0.7430172919},
{"learn":[0.06263325002],"iteration":859,"passed_time":4.531075211,"remaining_time":0.7376168948},
{"learn":[0.06262128587],"iteration":860,"passed_time":4.535833011,"remaining_time":0.7322657241},
{"learn":[0.06259422564],"iteration":861,"passed_time":4.541041679,"remaining_time":0.726988111},
{"learn":[0.0625695652],"iteration":862,"passed_time":4.546131367,"remaining_time":0.7216917698},
{"learn":[0.06253608419],"iteration":863,"passed_time":4.551233375,"remaining_time":0.7163978461},
{"learn":[0.06251181888],"iteration":864,"passed_time":4.556485517,"remaining_time":0.7111277975},
{"learn":[0.0624974898],"iteration":865,"passed_time":4.561573571,"remaining_time":0.7058324001},
{"learn":[0.06247200425],"iteration":866,"passed_time":4.566613884,"remaining_time":0.7005301576},
{"learn":[0.06244949376],"iteration":867,"passed_time":4.571553123,"remaining_time":0.6952131478},
{"learn":[0.06242485657],"iteration":868,"passed_time":4.576206894,"remaining_time":0.6898539736},
{"learn":[0.06241200339],"iteration":869,"passed_time":4.580984877,"remaining_time":0.6845149817},
{"learn":[0.06239801132],"iteration":870,"passed_time":4.586985429,"remaining_time":0.6793583471},
{"learn":[0.06239270038],"iteration":871,"passed_time":4.592010858,"remaining_time":0.6740566397},
{"learn":[0.06235594216],"iteration":872,"passed_time":4.596925963,"remaining_time":0.6687395158},
{"learn":[0.06235030582],"iteration":873,"passed_time":4.601881795,"remaining_time":0.6634291832},
{"learn":[0.06233624402],"iteration":874,"passed_time":4.606797187,"remaining_time":0.6581138838},
{"learn":[0.06230906757],"iteration":875,"passed_time":4.611905393,"remaining_time":0.6528267907},
{"learn":[0.06228807367],"iteration":876,"passed_time":4.617554376,"remaining_time":0.6476159501},
{"learn":[0.06227516819],"iteration":877,"passed_time":4.623778155,"remaining_time":0.6424839806},
{"learn":[0.06226687638],"iteration":878,"passed_time":4.629281171,"remaining_time":0.6372503091},
{"learn":[0.06226209421],"iteration":879,"passed_time":4.634296665,"remaining_time":0.6319495452},
{"learn":[0.06222470262],"iteration":880,"passed_time":4.639528376,"remaining_time":0.6266786343},
{"learn":[0.06220108811],"iteration":881,"passed_time":4.645164216,"remaining_time":0.6214618792},
{"learn":[0.06217838006],"iteration":882,"passed_time":4.650331467,"remaining_time":0.6161820856},
{"learn":[0.06214685142],"iteration":883,"passed_time":4.655437424,"remaining_time":0.6108945036},
{"learn":[0.06212364365],"iteration":884,"passed_time":4.661068203,"remaining_time":0.6056755292},
{"learn":[0.06209740853],"iteration":885,"passed_time":4.666057509,"remaining_time":0.600373088},
{"learn":[0.06209126085],"iteration":886,"passed_time":4.670671951,"remaining_time":0.5950235969},
{"learn":[0.06208474711],"iteration":887,"passed_time":4.675328804,"remaining_time":0.5896811105},
{"learn":[0.0620640844],"iteration":888,"passed_time":4.680219304,"remaining_time":0.5843693394},
{"learn":[0.06205926737],"iteration":889,"passed_time":4.684781714,"remaining_time":0.5790179646},
{"learn":[0.06203619324],"iteration":890,"passed_time":4.689461498,"remaining_time":0.5736827198},
{"learn":[0.06201400815],"iteration":891,"passed_time":4.69412672,"remaining_time":0.5683471813},
{"learn":[0.06200008],"iteration":892,"passed_time":4.698759767,"remaining_time":0.5630092889},
{"learn":[0.06198003904],"iteration":893,"passed_time":4.703417448,"remaining_time":0.5576758943},
{"learn":[0.06196733113],"iteration":894,"passed_time":4.70859137,"remaining_time":0.5524045741},
{"learn":[0.0619611021],"iteration":895,"passed_time":4.71412727,"remaining_time":0.5471754867},
{"learn":[0.06195643033],"iteration":896,"passed_time":4.719913528,"remaining_time":0.5419744631},
{"learn":[0.06193551196],"iteration":897,"passed_time":4.725503306,"remaining_time":0.5367498187},
{"learn":[0.06192918416],"iteration":898,"passed_time":4.731066079,"remaining_time":0.5315213281},
{"learn":[0.06189936967],"iteration":899,"passed_time":4.736878408,"remaining_time":0.5263198231},
{"learn":[0.06188604583],"iteration":900,"passed_time":4.742151907,"remaining_time":0.5210577568},
{"learn":[0.06184936895],"iteration":901,"passed_time":4.747603289,"remaining_time":0.5158149915},
{"learn":[0.06182981028],"iteration":902,"passed_time":4.753391612,"remaining_time":0.5106079583},
{"learn":[0.06182301181],"iteration":903,"passed_time":4.758841928,"remaining_time":0.5053637446},
{"learn":[0.06180388893],"iteration":904,"passed_time":4.764277515,"remaining_time":0.5001175292},
{"learn":[0.06178324947],"iteration":905,"passed_time":4.769436749,"remaining_time":0.4948422234},
{"learn":[0.06177331906],"iteration":906,"passed_time":4.774392808,"remaining_time":0.4895463408},
{"learn":[0.06174474805],"iteration":907,"passed_time":4.780216942,"remaining_time":0.4843391615},
{"learn":[0.06172578787],"iteration":908,"passed_time":4.786285427,"remaining_time":0.4791550868},
{"learn":[0.06171600272],"iteration":909,"passed_time":4.791621494,"remaining_time":0.4738966313},
{"learn":[0.06169154566],"iteration":910,"passed_time":4.797467808,"remaining_time":0.4686878539},
{"learn":[0.06167011014],"iteration":911,"passed_time":4.802381902,"remaining_time":0.4633877274},
{"learn":[0.06164685589],"iteration":912,"passed_time":4.807273423,"remaining_time":0.4580862955},
{"learn":[0.061627181],"iteration":913,"passed_time":4.81240652,"remaining_time":0.4528084909},
{"learn":[0.06159367674],"iteration":914,"passed_time":4.817497093,"remaining_time":0.4475270524},
{"learn":[0.06156428643],"iteration":915,"passed_time":4.8224475,"remaining_time":0.4422331769},
{"learn":[0.06155045706],"iteration":916,"passed_time":4.827424702,"remaining_time":0.4369424757},
{"learn":[0.06154451857],"iteration":917,"passed_time":4.83262836,"remaining_time":0.4316726857},
{"learn":[0.06152361182],"iteration":918,"passed_time":4.837848495,"remaining_time":0.426404492},
{"learn":[0.06151393126],"iteration":919,"passed_time":4.843295332,"remaining_time":0.4211561158},
{"learn":[0.06150791142],"iteration":920,"passed_time":4.848507576,"remaining_time":0.4158871862},
{"learn":[0.06149990433],"iteration":921,"passed_time":4.853866946,"remaining_time":0.4106308263},
{"learn":[0.06148422718],"iteration":922,"passed_time":4.859506229,"remaining_time":0.4053975944},
{"learn":[0.06145456958],"iteration":923,"passed_time":4.865481451,"remaining_time":0.400191115},
{"learn":[0.0614237789],"iteration":924,"passed_time":4.87120438,"remaining_time":0.3949625173},
{"learn":[0.06139231418],"iteration":925,"passed_time":4.876781589,"remaining_time":0.3897212069},
{"learn":[0.06136907155],"iteration":926,"passed_time":4.881859239,"remaining_time":0.3844398322},
{"learn":[0.06134975692],"iteration":927,"passed_time":4.887017822,"remaining_time":0.3791651758},
{"learn":[0.06133108727],"iteration":928,"passed_time":4.892441044,"remaining_time":0.3739109948},
{"learn":[0.0613196519],"iteration":929,"passed_time":4.897348683,"remaining_time":0.3686176428},
{"learn":[0.06130104036],"iteration":930,"passed_time":4.902269197,"remaining_time":0.3633260737},
{"learn":[0.06129613035],"iteration":931,"passed_time":4.907161245,"remaining_time":0.3580332239},
{"learn":[0.06126869242],"iteration":932,"passed_time":4.912307212,"remaining_time":0.3527594675},
{"learn":[0.06125107451],"iteration":933,"passed_time":4.917261373,"remaining_time":0.3474724311},
{"learn":[0.06123270702],"iteration":934,"passed_time":4.922138382,"remaining_time":0.3421807431},
{"learn":[0.06122178298],"iteration":935,"passed_time":4.926953404,"remaining_time":0.3368857028},
{"learn":[0.06121680905],"iteration":936,"passed_time":4.932178076,"remaining_time":0.3316192303},
{"learn":[0.06121047544],"iteration":937,"passed_time":4.937248183,"remaining_time":0.3263426304},
{"learn":[0.06120279375],"iteration":938,"passed_time":4.942337846,"remaining_time":0.3210677408},
{"learn":[0.06119389182],"iteration":939,"passed_time":4.947455687,"remaining_time":0.3157950438},
{"learn":[0.06116466421],"iteration":940,"passed_time":4.952687647,"remaining_time":0.3105298312},
{"learn":[0.0611569767],"iteration":941,"passed_time":4.957803322,"remaining_time":0.3052575294},
{"learn":[0.06113210709],"iteration":942,"passed_time":4.963315195,"remaining_time":0.3000095081},
{"learn":[0.06112984093],"iteration":943,"passed_time":4.968889012,"remaining_time":0.2947646024},
{"learn":[0.06112369906],"iteration":944,"passed_time":4.974158896,"remaining_time":0.2895013114},
{"learn":[0.06111764436],"iteration":945,"passed_time":4.97944679,"remaining_time":0.2842390345},
{"learn":[0.0611119964],"iteration":946,"passed_time":4.984609764,"remaining_time":0.2789697122},
{"learn":[0.06109384971],"iteration":947,"passed_time":4.990169474,"remaining_time":0.2737223762},
{"learn":[0.0610811418],"iteration":948,"passed_time":4.995821518,"remaining_time":0.268479344},
{"learn":[0.06107523817],"iteration":949,"passed_time":5.00116057,"remaining_time":0.2632189773},
{"learn":[0.06105796308],"iteration":950,"passed_time":5.006449443,"remaining_time":0.2579558599},
{"learn":[0.06105124015],"iteration":951,"passed_time":5.011545882,"remaining_time":0.2526829856},
{"learn":[0.06102730024],"iteration":952,"passed_time":5.016751329,"remaining_time":0.2474158578},
{"learn":[0.06102320954],"iteration":953,"passed_time":5.021859277,"remaining_time":0.242144158},
{"learn":[0.06099590525],"iteration":954,"passed_time":5.026990284,"remaining_time":0.2368738877},
{"learn":[0.06099355775],"iteration":955,"passed_time":5.032014364,"remaining_time":0.2315989875},
{"learn":[0.06097707291],"iteration":956,"passed_time":5.037114181,"remaining_time":0.2263280144},
{"learn":[0.06096048348],"iteration":957,"passed_time":5.04270616,"remaining_time":0.2210789757},
{"learn":[0.06095218586],"iteration":958,"passed_time":5.048519085,"remaining_time":0.2158386679},
{"learn":[0.06093979172],"iteration":959,"passed_time":5.05436696,"remaining_time":0.2105986233},
{"learn":[0.06093011117],"iteration":960,"passed_time":5.060319878,"remaining_time":0.2053615767},
{"learn":[0.06091799013],"iteration":961,"passed_time":5.066198211,"remaining_time":0.2001200957},
{"learn":[0.06089161555],"iteration":962,"passed_time":5.071607648,"remaining_time":0.1948592762},
{"learn":[0.06087658919],"iteration":963,"passed_time":5.076727225,"remaining_time":0.1895873238},
{"learn":[0.06086113865],"iteration":964,"passed_time":5.08321082,"remaining_time":0.1843651593},
{"learn":[0.06084240509],"iteration":965,"passed_time":5.088519345,"remaining_time":0.1790990246},
{"learn":[0.06082609457],"iteration":966,"passed_time":5.094116606,"remaining_time":0.1738426556},
{"learn":[0.06079865083],"iteration":967,"passed_time":5.099333462,"remaining_time":0.168573007},
{"learn":[0.06077533847],"iteration":968,"passed_time":5.105016075,"remaining_time":0.1633183677},
{"learn":[0.06076246205],"iteration":969,"passed_time":5.110405171,"remaining_time":0.1580537682},
{"learn":[0.0607565468],"iteration":970,"passed_time":5.115603736,"remaining_time":0.1527832218},
{"learn":[0.06075185179],"iteration":971,"passed_time":5.120721265,"remaining_time":0.1475104891},
{"learn":[0.06074625612],"iteration":972,"passed_time":5.12561808,"remaining_time":0.1422319508},
{"learn":[0.06074249663],"iteration":973,"passed_time":5.130732987,"remaining_time":0.1369600181},
{"learn":[0.06073046856],"iteration":974,"passed_time":5.135921148,"remaining_time":0.1316902858},
{"learn":[0.06071917264],"iteration":975,"passed_time":5.140819389,"remaining_time":0.1264135915},
{"learn":[0.06070763268],"iteration":976,"passed_time":5.145772921,"remaining_time":0.1211389736},
{"learn":[0.06069228092],"iteration":977,"passed_time":5.150598436,"remaining_time":0.1158621325},
{"learn":[0.06068784157],"iteration":978,"passed_time":5.155167093,"remaining_time":0.1105807037},
{"learn":[0.06066397139],"iteration":979,"passed_time":5.160081572,"remaining_time":0.1053077872},
{"learn":[0.06065572025],"iteration":980,"passed_time":5.165422122,"remaining_time":0.1000438535},
{"learn":[0.06064065903],"iteration":981,"passed_time":5.170550024,"remaining_time":0.09477586602},
{"learn":[0.06062565591],"iteration":982,"passed_time":5.175475304,"remaining_time":0.08950465937},
{"learn":[0.06060342433],"iteration":983,"passed_time":5.180651205,"remaining_time":0.08423823097},
{"learn":[0.06059632951],"iteration":984,"passed_time":5.185600862,"remaining_time":0.07896854104},
{"learn":[0.06058276163],"iteration":985,"passed_time":5.19064102,"remaining_time":0.07370078527},
{"learn":[0.06056684623],"iteration":986,"passed_time":5.196153555,"remaining_time":0.06843971248},
{"learn":[0.06055816511],"iteration":987,"passed_time":5.201786657,"remaining_time":0.06317959503},
{"learn":[0.06054325496],"iteration":988,"passed_time":5.207509054,"remaining_time":0.05791971648},
{"learn":[0.06052712457],"iteration":989,"passed_time":5.212848491,"remaining_time":0.05265503526},
{"learn":[0.06052034353],"iteration":990,"passed_time":5.218131321,"remaining_time":0.0473896891},
{"learn":[0.06051382397],"iteration":991,"passed_time":5.223706433,"remaining_time":0.04212666478},
{"learn":[0.06050287669],"iteration":992,"passed_time":5.229037957,"remaining_time":0.03686129476},
{"learn":[0.06049793763],"iteration":993,"passed_time":5.23384389,"remaining_time":0.03159261906},
{"learn":[0.0604853808],"iteration":994,"passed_time":5.239080881,"remaining_time":0.0263270396},
{"learn":[0.06047334693],"iteration":995,"passed_time":5.244106684,"remaining_time":0.02106066941},
{"learn":[0.06047027309],"iteration":996,"passed_time":5.248641126,"remaining_time":0.01579330329},
{"learn":[0.0604623183],"iteration":997,"passed_time":5.253324892,"remaining_time":0.01052770519},
{"learn":[0.0604499416],"iteration":998,"passed_time":5.258092777,"remaining_time":0.005263356133},
{"learn":[0.06044522334],"iteration":999,"passed_time":5.262739958,"remaining_time":0}
]}